02_rtl/Question2/LOPD_4bit.sv
module LOPD_4bit(
    input logic [3:0]       i_data  ,
    output logic [1:0]      o_pos_one,
    output logic            o_zero_flag
);

/////////////////// LDO ///////////////////
// D[3] | D[2] | D[1] | D[0] |PO[3] | PO[2] | PO[1] | PO[0] | ZERO_FLAG |
//   0  |   0  |   0  |   0  |  0   |   0   |   0   |   0   |     1     |
//   0  |   0  |   0  |   1  |  0   |   0   |   0   |   1   |     0     |
//   0  |   0  |   1  |   X  |  0   |   0   |   1   |   0   |     0     |
//   0  |   1  |   X  |   X  |  0   |   1   |   0   |   0   |     0     |
//   1  |   X  |   X  |   X  |  1   |   0   |   0   |   0   |     0     |
/////////////////// LDOD ///////////////////
// D[3] | D[2] | D[1] | D[0] | PO[1] | PO[0] | ZERO_FLAG |
//   0  |   0  |   0  |   0  |   0   |   0   |     1     |
//   0  |   0  |   0  |   1  |   0   |   0   |     0     |
//   0  |   0  |   1  |   X  |   0   |   1   |     0     |
//   0  |   1  |   X  |   X  |   1   |   0   |     0     |
//   1  |   X  |   X  |   X  |   1   |   1   |     0     |

assign o_zero_flag = ~((o_pos_one[1])|(i_data[1]|i_data[0])) ;
assign o_pos_one[1] = i_data[3] | i_data[2];
assign o_pos_one[0] = ((~(i_data[3] | i_data[2])) & (i_data[1])) |  (i_data[3]);

endmodule

02_rtl/Question2/LOPD_8bit.sv
module LOPD_8bit(
    input logic [7:0]       i_data  ,
    output logic [2:0]      o_pos_one,
    output logic            o_zero_flag
);

////////////////////////////////////////////////////////////
// LOPD_4bit_unit_0
////////////////////////////////////////////////////////////
logic w_zero_flag_0;
logic [1:0] w_pos_one_0;
LOPD_4bit LOPD_4bit_unit_0 (
    .i_data         (i_data[3:0]),
    .o_pos_one      (w_pos_one_0),
    .o_zero_flag    (w_zero_flag_0)
);

////////////////////////////////////////////////////////////
// LOPD_4bit_unit_1
////////////////////////////////////////////////////////////
logic w_zero_flag_1;
logic [1:0] w_pos_one_1;
LOPD_4bit LOPD_4bit_unit_1 (
    .i_data         (i_data[7:4]),
    .o_pos_one      (w_pos_one_1),
    .o_zero_flag    (w_zero_flag_1)
);

////////////////////////////////////////////////////////////
// LOD_8bit_unit
////////////////////////////////////////////////////////////
assign o_zero_flag = w_zero_flag_0 & w_zero_flag_1;
assign o_pos_one[2] = ~(w_zero_flag_1);
assign o_pos_one[1] = (w_zero_flag_1) ? w_pos_one_0[1] : w_pos_one_1[1];
assign o_pos_one[0] = (w_zero_flag_1) ? w_pos_one_0[0] : w_pos_one_1[0];

endmodule

02_rtl/Question2/LOPD_16bit.sv
module LOPD_16bit(
    input logic [15:0]       i_data  ,
    output logic [3:0]      o_pos_one,
    output logic            o_zero_flag
);


////////////////////////////////////////////////////////////
// LOPD_8bit_unit_0
////////////////////////////////////////////////////////////
logic [2:0]         w_pos_one_0;  
logic               w_zero_flag_0;
LOPD_8bit LOPD_8bit_unit_0(
    .i_data         (i_data[7:0]),
    .o_pos_one      (w_pos_one_0),
    .o_zero_flag    (w_zero_flag_0)
);
////////////////////////////////////////////////////////////
// LOPD_8bit_unit_1
////////////////////////////////////////////////////////////
logic [2:0]         w_pos_one_1;  
logic               w_zero_flag_1;
LOPD_8bit LOPD_8bit_unit_1(
    .i_data         (i_data[15:8]),
    .o_pos_one      (w_pos_one_1),
    .o_zero_flag    (w_zero_flag_1)
);

////////////////////////////////////////////////////////////
// LOD_16bit_unit
////////////////////////////////////////////////////////////
assign o_zero_flag = w_zero_flag_0 & w_zero_flag_1;
assign o_pos_one[3] = ~(w_zero_flag_1);
assign o_pos_one[2] = w_zero_flag_1 ? w_pos_one_0[2] : w_pos_one_1[2];
assign o_pos_one[1] = w_zero_flag_1 ? w_pos_one_0[1] : w_pos_one_1[1];
assign o_pos_one[0] = w_zero_flag_1 ? w_pos_one_0[0] : w_pos_one_1[0];
endmodule

02_rtl/Question2/Question2.sv
module Question2 #(
    parameter SIZE_DATA     = 24    ,
    parameter SIZE_LOPD     = 5      
)(
    input logic [SIZE_DATA-1:0]     i_data          ,
    output logic [SIZE_LOPD-1:0]    o_one_position  ,
    output logic                    o_zero_flag      
);

logic [15:0]     LOPD16_i_data;
assign LOPD16_i_data = i_data[15:0];
logic [3:0]      LOPD16_o_pos_one;
logic            LOPD16_o_zero_flag;
logic [7:0]      LOPD8_i_data;
assign LOPD8_i_data = i_data[23:16];
logic [2:0]      LOPD8_o_pos_one;
logic            LOPD8_o_zero_flag;
LOPD_16bit LOPD_16bit_UNIT_LSB (
    .i_data             (LOPD16_i_data),
    .o_pos_one          (LOPD16_o_pos_one),
    .o_zero_flag        (LOPD16_o_zero_flag)
);

LOPD_8bit LOPD_8bit_UNIT_MSB (
    .i_data             (LOPD8_i_data),
    .o_pos_one          (LOPD8_o_pos_one),
    .o_zero_flag        (LOPD8_o_zero_flag)
);

assign o_zero_flag = LOPD16_o_zero_flag & LOPD8_o_zero_flag;
assign o_one_position[0] = LOPD8_o_zero_flag ? LOPD16_o_pos_one[0] : LOPD8_o_pos_one[0];
assign o_one_position[1] = LOPD8_o_zero_flag ? LOPD16_o_pos_one[1] : LOPD8_o_pos_one[1];
assign o_one_position[2] = LOPD8_o_zero_flag ? LOPD16_o_pos_one[2] : LOPD8_o_pos_one[2];
assign o_one_position[3] = LOPD8_o_zero_flag ? LOPD16_o_pos_one[3] : 1'b0;
assign o_one_position[4] = ~LOPD8_o_zero_flag;

endmodule

03_test/Question2/tb_Question2.sv
`timescale 1ns/1ps
module tb_Question2();

parameter SIZE_DATA = 24;
parameter SIZE_LOP  = 5;

int test_count = 0;
int test_pass  = 0;

logic i_clk, i_rst_n;
logic [SIZE_DATA-1:0] i_addr;
logic [SIZE_DATA-1:0] i_data;
logic [SIZE_DATA-1:0] o_addr;  
logic [SIZE_LOP-1:0]  o_one_position;
logic                 o_zero_flag;

function automatic logic [SIZE_LOP-1:0] Test_LOPD(
    input logic [SIZE_DATA-1:0]     f_i_data
);
    logic [SIZE_DATA-1:0] t_temp;
    int cnt_position_1;
    begin
        t_temp = f_i_data;
        cnt_position_1 = 0;

        if(t_temp == 0) begin
            Test_LOPD = '0;
        end else begin
            while (t_temp[SIZE_DATA-1] == 0) begin
                t_temp = t_temp << 1;
                cnt_position_1 ++;
            end
            Test_LOPD = SIZE_DATA - cnt_position_1 - 1;
        end
    end

endfunction

//===================== DUT =====================//

Question2 #(
    .SIZE_DATA (SIZE_DATA),
    .SIZE_LOPD  (SIZE_LOP)
) DUT (
    .i_data         (i_data),
    .o_one_position (o_one_position),
    .o_zero_flag    (o_zero_flag)
);

//===================== CLOCK =====================//
initial begin
    i_clk = 0;
    forever #5 i_clk = ~i_clk; // 10ns period = 100MHz
end

//===================== DUMP WAVE =====================//
// initial begin
//     $dumpfile("tb_Question2.vcd");
//     $dumpvars(0, tb_Question2);
// end
//===================== TEST SEQUENCE =====================//
int bit_pos;
initial begin
    i_rst_n = 0;
    i_addr  = '0;
    i_data  = '0;

    // Reset phase
    #20;
    i_rst_n = 1;
    #10;

    repeat (1) begin
        @(posedge i_clk);
        #1;
        i_addr = i_addr + 1;
        i_data  = 24'b0;
        @(negedge i_clk);
        #1;
        $display("[TIME: %5t] [%s] i_data = %b (%d) \t| o_one_position = %b (%d) \t| o_zero_flag = %b", $time, "Zero", i_data, i_data, o_one_position, o_one_position, o_zero_flag);
        $display("=> %4s: Expect: %8h, DUT: %8h ", (Test_LOPD(i_data) == o_one_position) ? "PASS" : "FAIL", o_one_position, Test_LOPD(i_data));
        test_count = test_count + 1;
        test_pass  = (Test_LOPD(i_data) == o_one_position) ? test_pass + 1 : test_pass;
    end

    bit_pos = 1;
    repeat (24) begin
        @(posedge i_clk);
        #1;
        i_addr = i_addr + 1;
        i_data  = bit_pos;
        @(negedge i_clk);
        #1;
        $display("[TIME: %5t] [%s] i_data = %b (%d) \t| o_one_position = %b (%d) \t| o_zero_flag = %b", $time, "Direcly", i_data, i_data, o_one_position, o_one_position, o_zero_flag);
        $display("=> %4s: Expect: %8h, DUT: %8h ", (Test_LOPD(i_data) == o_one_position) ? "PASS" : "FAIL", o_one_position, Test_LOPD(i_data));
        test_count = test_count + 1;
        test_pass  = (Test_LOPD(i_data) == o_one_position) ? test_pass + 1 : test_pass;
        bit_pos = bit_pos << 1'b1;
    end
    repeat (100) begin
        @(posedge i_clk);
        #1;
        bit_pos = $urandom_range(0, SIZE_DATA-1);
        i_data = 24'b1 << bit_pos;
        if ($urandom_range(0, 1)) begin
            i_data |= $urandom_range(0, (1 << SIZE_DATA) - 1);
        end
        #5;
        $display("[TIME: %5t] [%s] i_data = %b (%d) \t| o_one_position = %b (%d) \t| o_zero_flag = %b", $time, "Random", i_data, i_data, o_one_position, o_one_position, o_zero_flag);
        $display("=> %4s: Expect: %8h, DUT: %8h ", (Test_LOPD(i_data) == o_one_position) ? "PASS" : "FAIL", o_one_position, Test_LOPD(i_data));
        test_count = test_count + 1;
        test_pass  = (Test_LOPD(i_data) == o_one_position) ? test_pass + 1 : test_pass;
        i_addr = i_addr + 1;
    end

    #10;
    $display("\n================================");
    $display("==========TEST SUMMARY==========");
    $display("Total test cases: %6d    ", test_count);
    $display("Passed          : %6d    ", test_pass);
    $display("Failed          : %6d    ", test_count - test_pass);
    $display("Pass rate       : %0.2f%%", (test_pass * 100.0) / (test_count));
    $display("================================");
    #100;

    $finish;
end

endmodule

03_test/Question3/tb_Question2.vcd
$date
	Fri Oct 24 23:18:40 2025
$end
$version
	Questa Intel Starter FPGA Edition Version 2024.3
$end
$timescale
	1ps
$end

$scope module tb_Question2 $end
$var parameter 32 ! SIZE_DATA $end
$var parameter 32 " SIZE_LOP $end
$var integer 32 # test_count $end
$var integer 32 $ test_pass $end
$var reg 1 % i_clk $end
$var reg 1 & i_rst_n $end
$var reg 24 ' i_addr [23:0] $end
$var reg 24 ( i_data [23:0] $end
$var reg 24 ) o_addr [23:0] $end
$var reg 5 * o_one_position [4:0] $end
$var reg 1 + o_zero_flag $end
$var integer 32 , bit_pos $end

$scope function Test_LOPD $end
$upscope $end

$scope module DUT $end
$var parameter 32 - SIZE_DATA $end
$var parameter 32 . SIZE_LOPD $end
$var wire 1 / i_data [23] $end
$var wire 1 0 i_data [22] $end
$var wire 1 1 i_data [21] $end
$var wire 1 2 i_data [20] $end
$var wire 1 3 i_data [19] $end
$var wire 1 4 i_data [18] $end
$var wire 1 5 i_data [17] $end
$var wire 1 6 i_data [16] $end
$var wire 1 7 i_data [15] $end
$var wire 1 8 i_data [14] $end
$var wire 1 9 i_data [13] $end
$var wire 1 : i_data [12] $end
$var wire 1 ; i_data [11] $end
$var wire 1 < i_data [10] $end
$var wire 1 = i_data [9] $end
$var wire 1 > i_data [8] $end
$var wire 1 ? i_data [7] $end
$var wire 1 @ i_data [6] $end
$var wire 1 A i_data [5] $end
$var wire 1 B i_data [4] $end
$var wire 1 C i_data [3] $end
$var wire 1 D i_data [2] $end
$var wire 1 E i_data [1] $end
$var wire 1 F i_data [0] $end
$var reg 5 G o_one_position [4:0] $end
$var reg 1 H o_zero_flag $end
$var reg 16 I LOPD16_i_data [15:0] $end
$var reg 4 J LOPD16_o_pos_one [3:0] $end
$var reg 1 K LOPD16_o_zero_flag $end
$var reg 8 L LOPD8_i_data [7:0] $end
$var reg 3 M LOPD8_o_pos_one [2:0] $end
$var reg 1 N LOPD8_o_zero_flag $end

$scope module LOPD_16bit_UNIT_LSB $end
$var wire 1 O i_data [15] $end
$var wire 1 P i_data [14] $end
$var wire 1 Q i_data [13] $end
$var wire 1 R i_data [12] $end
$var wire 1 S i_data [11] $end
$var wire 1 T i_data [10] $end
$var wire 1 U i_data [9] $end
$var wire 1 V i_data [8] $end
$var wire 1 W i_data [7] $end
$var wire 1 X i_data [6] $end
$var wire 1 Y i_data [5] $end
$var wire 1 Z i_data [4] $end
$var wire 1 [ i_data [3] $end
$var wire 1 \ i_data [2] $end
$var wire 1 ] i_data [1] $end
$var wire 1 ^ i_data [0] $end
$var reg 4 _ o_pos_one [3:0] $end
$var reg 1 ` o_zero_flag $end
$var reg 3 a w_pos_one_0 [2:0] $end
$var reg 1 b w_zero_flag_0 $end
$var reg 3 c w_pos_one_1 [2:0] $end
$var reg 1 d w_zero_flag_1 $end

$scope module LOPD_8bit_unit_0 $end
$var wire 1 W i_data [7] $end
$var wire 1 X i_data [6] $end
$var wire 1 Y i_data [5] $end
$var wire 1 Z i_data [4] $end
$var wire 1 [ i_data [3] $end
$var wire 1 \ i_data [2] $end
$var wire 1 ] i_data [1] $end
$var wire 1 ^ i_data [0] $end
$var reg 3 e o_pos_one [2:0] $end
$var reg 1 f o_zero_flag $end
$var reg 1 g w_zero_flag_0 $end
$var reg 2 h w_pos_one_0 [1:0] $end
$var reg 1 i w_zero_flag_1 $end
$var reg 2 j w_pos_one_1 [1:0] $end

$scope module LOPD_4bit_unit_0 $end
$var wire 1 [ i_data [3] $end
$var wire 1 \ i_data [2] $end
$var wire 1 ] i_data [1] $end
$var wire 1 ^ i_data [0] $end
$var reg 2 k o_pos_one [1:0] $end
$var reg 1 l o_zero_flag $end
$upscope $end

$scope module LOPD_4bit_unit_1 $end
$var wire 1 W i_data [3] $end
$var wire 1 X i_data [2] $end
$var wire 1 Y i_data [1] $end
$var wire 1 Z i_data [0] $end
$var reg 2 m o_pos_one [1:0] $end
$var reg 1 n o_zero_flag $end
$upscope $end
$upscope $end

$scope module LOPD_8bit_unit_1 $end
$var wire 1 O i_data [7] $end
$var wire 1 P i_data [6] $end
$var wire 1 Q i_data [5] $end
$var wire 1 R i_data [4] $end
$var wire 1 S i_data [3] $end
$var wire 1 T i_data [2] $end
$var wire 1 U i_data [1] $end
$var wire 1 V i_data [0] $end
$var reg 3 o o_pos_one [2:0] $end
$var reg 1 p o_zero_flag $end
$var reg 1 q w_zero_flag_0 $end
$var reg 2 r w_pos_one_0 [1:0] $end
$var reg 1 s w_zero_flag_1 $end
$var reg 2 t w_pos_one_1 [1:0] $end

$scope module LOPD_4bit_unit_0 $end
$var wire 1 S i_data [3] $end
$var wire 1 T i_data [2] $end
$var wire 1 U i_data [1] $end
$var wire 1 V i_data [0] $end
$var reg 2 u o_pos_one [1:0] $end
$var reg 1 v o_zero_flag $end
$upscope $end

$scope module LOPD_4bit_unit_1 $end
$var wire 1 O i_data [3] $end
$var wire 1 P i_data [2] $end
$var wire 1 Q i_data [1] $end
$var wire 1 R i_data [0] $end
$var reg 2 w o_pos_one [1:0] $end
$var reg 1 x o_zero_flag $end
$upscope $end
$upscope $end
$upscope $end

$scope module LOPD_8bit_UNIT_MSB $end
$var wire 1 y i_data [7] $end
$var wire 1 z i_data [6] $end
$var wire 1 { i_data [5] $end
$var wire 1 | i_data [4] $end
$var wire 1 } i_data [3] $end
$var wire 1 ~ i_data [2] $end
$var wire 1 !! i_data [1] $end
$var wire 1 "! i_data [0] $end
$var reg 3 #! o_pos_one [2:0] $end
$var reg 1 $! o_zero_flag $end
$var reg 1 %! w_zero_flag_0 $end
$var reg 2 &! w_pos_one_0 [1:0] $end
$var reg 1 '! w_zero_flag_1 $end
$var reg 2 (! w_pos_one_1 [1:0] $end

$scope module LOPD_4bit_unit_0 $end
$var wire 1 } i_data [3] $end
$var wire 1 ~ i_data [2] $end
$var wire 1 !! i_data [1] $end
$var wire 1 "! i_data [0] $end
$var reg 2 )! o_pos_one [1:0] $end
$var reg 1 *! o_zero_flag $end
$upscope $end

$scope module LOPD_4bit_unit_1 $end
$var wire 1 y i_data [3] $end
$var wire 1 z i_data [2] $end
$var wire 1 { i_data [1] $end
$var wire 1 | i_data [0] $end
$var reg 2 +! o_pos_one [1:0] $end
$var reg 1 ,! o_zero_flag $end
$upscope $end
$upscope $end
$upscope $end
$upscope $end
$enddefinitions $end
#0
$dumpvars
0%
0&
b0 '
b0 (
bx )
b0 *
1+
b0 G
1H
b0 I
b0 J
1K
b0 L
b0 M
1N
b0 _
1`
b0 a
1b
b0 e
1f
1g
b0 h
b0 k
1l
1i
b0 j
b0 m
1n
b0 c
1d
b0 o
1p
1q
b0 r
b0 u
1v
1s
b0 t
b0 w
1x
b0 #!
1$!
1%!
b0 &!
b0 )!
1*!
1'!
b0 (!
b0 +!
1,!
b11000 !
b101 "
b11000 -
b101 .
b0 #
b0 $
b0 ,
0F
0E
0D
0C
0B
0A
0@
0?
0>
0=
0<
0;
0:
09
08
07
06
05
04
03
02
01
00
0/
0"!
0!!
0~
0}
0|
0{
0z
0y
0^
0]
0\
0[
0Z
0Y
0X
0W
0V
0U
0T
0S
0R
0Q
0P
0O
$end
#5000
1%
#10000
0%
#15000
1%
#20000
1&
0%
#25000
1%
#30000
0%
#35000
1%
#36000
b1 '
#40000
0%
#41000
b1 #
b1 $
b1 ,
#45000
1%
#46000
b10 '
b1 (
1F
b1 I
1^
0l
0g
0f
0b
0`
0K
0H
0+
#50000
0%
#51000
b10 #
b10 $
b10 ,
#55000
1%
#56000
b11 '
b10 (
0F
1E
b10 I
0^
1]
b1 k
b1 h
b1 e
b1 a
b1 _
b1 J
b1 G
b1 *
#60000
0%
#61000
b11 #
b11 $
b100 ,
#65000
1%
#66000
b100 '
b100 (
0E
1D
b100 I
0]
1\
b11 k
b10 k
b10 h
b11 e
b10 e
b10 a
b11 _
b10 _
b10 J
b11 G
b10 G
b10 *
#70000
0%
#71000
b100 #
b100 $
b1000 ,
#75000
1%
#76000
b101 '
b1000 (
0D
1C
b1000 I
0\
1[
b11 k
b11 h
b11 e
b11 a
b11 _
b11 J
b11 G
b11 *
#80000
0%
#81000
b101 #
b101 $
b10000 ,
#85000
1%
#86000
b110 '
b10000 (
0C
1B
b10000 I
0[
1Z
0n
b1 k
b0 k
b0 h
1l
0i
b111 e
1g
b101 e
b100 e
b100 a
b111 _
b101 _
b100 _
b100 J
b111 G
b101 G
b100 G
b100 *
#90000
0%
#91000
b110 #
b110 $
b100000 ,
#95000
1%
#96000
b111 '
b100000 (
0B
1A
b100000 I
0Z
1Y
b1 m
b1 j
b101 e
b101 a
b101 _
b101 J
b101 G
b101 *
#100000
0%
#101000
b111 #
b111 $
b1000000 ,
#105000
1%
#106000
b1000 '
b1000000 (
0A
1@
b1000000 I
0Y
1X
b11 m
b10 m
b10 j
b111 e
b110 e
b110 a
b111 _
b110 _
b110 J
b111 G
b110 G
b110 *
#110000
0%
#111000
b1000 #
b1000 $
b10000000 ,
#115000
1%
#116000
b1001 '
b10000000 (
0@
1?
b10000000 I
0X
1W
b11 m
b11 j
b111 e
b111 a
b111 _
b111 J
b111 G
b111 *
#120000
0%
#121000
b1001 #
b1001 $
b100000000 ,
#125000
1%
#126000
b1010 '
b100000000 (
0?
1>
b100000000 I
0W
1V
0v
b1 m
b0 m
b0 j
1n
0q
0p
1i
b101 e
b100 e
b100 a
b0 e
1f
0d
b11 _
b1011 _
1b
b0 a
b1001 _
b1000 _
b1000 J
b1111 G
b1011 G
b1001 G
b1000 G
b1000 *
#130000
0%
#131000
b1010 #
b1010 $
b1000000000 ,
#135000
1%
#136000
b1011 '
b1000000000 (
0>
1=
b1000000000 I
0V
1U
b1 u
b1 r
b1 o
b1 c
b1001 _
b1001 J
b1001 G
b1001 *
#140000
0%
#141000
b1011 #
b1011 $
b10000000000 ,
#145000
1%
#146000
b1100 '
b10000000000 (
0=
1<
b10000000000 I
0U
1T
b11 u
b10 u
b10 r
b11 o
b10 o
b10 c
b1011 _
b1010 _
b1010 J
b1011 G
b1010 G
b1010 *
#150000
0%
#151000
b1100 #
b1100 $
b100000000000 ,
#155000
1%
#156000
b1101 '
b100000000000 (
0<
1;
b100000000000 I
0T
1S
b11 u
b11 r
b11 o
b11 c
b1011 _
b1011 J
b1011 G
b1011 *
#160000
0%
#161000
b1101 #
b1101 $
b1000000000000 ,
#165000
1%
#166000
b1110 '
b1000000000000 (
0;
1:
b1000000000000 I
0S
1R
0x
b1 u
b0 u
b0 r
1v
0s
b111 o
1q
b101 o
b100 o
b100 c
b1111 _
b1101 _
b1100 _
b1100 J
b1111 G
b1101 G
b1100 G
b1100 *
#170000
0%
#171000
b1110 #
b1110 $
b10000000000000 ,
#175000
1%
#176000
b1111 '
b10000000000000 (
0:
19
b10000000000000 I
0R
1Q
b1 w
b1 t
b101 o
b101 c
b1101 _
b1101 J
b1101 G
b1101 *
#180000
0%
#181000
b1111 #
b1111 $
b100000000000000 ,
#185000
1%
#186000
b10000 '
b100000000000000 (
09
18
b100000000000000 I
0Q
1P
b11 w
b10 w
b10 t
b111 o
b110 o
b110 c
b1111 _
b1110 _
b1110 J
b1111 G
b1110 G
b1110 *
#190000
0%
#191000
b10000 #
b10000 $
b1000000000000000 ,
#195000
1%
#196000
b10001 '
b1000000000000000 (
08
17
b1000000000000000 I
0P
1O
b11 w
b11 t
b111 o
b111 c
b1111 _
b1111 J
b1111 G
b1111 *
#200000
0%
#201000
b10001 #
b10001 $
b10000000000000000 ,
#205000
1%
#206000
b10010 '
b10000000000000000 (
07
16
b1 L
b0 I
0O
1"!
0*!
b1 w
b0 w
b0 t
1x
0%!
0$!
1s
b101 o
b100 o
b100 c
b0 o
1p
0N
b11111 G
b10111 G
b10011 G
b10001 G
b10000 G
1d
b0 c
b1101 _
b1100 _
b1100 J
b1000 _
b0 _
1`
b10000 *
1K
b0 J
#210000
0%
#211000
b10010 #
b10010 $
b100000000000000000 ,
#215000
1%
#216000
b10011 '
b100000000000000000 (
06
15
b10 L
0"!
1!!
b1 )!
b1 &!
b1 #!
b1 M
b10001 G
b10001 *
#220000
0%
#221000
b10011 #
b10011 $
b1000000000000000000 ,
#225000
1%
#226000
b10100 '
b1000000000000000000 (
05
14
b100 L
0!!
1~
b11 )!
b10 )!
b10 &!
b11 #!
b10 #!
b10 M
b10011 G
b10010 G
b10010 *
#230000
0%
#231000
b10100 #
b10100 $
b10000000000000000000 ,
#235000
1%
#236000
b10101 '
b10000000000000000000 (
04
13
b1000 L
0~
1}
b11 )!
b11 &!
b11 #!
b11 M
b10011 G
b10011 *
#240000
0%
#241000
b10101 #
b10101 $
b100000000000000000000 ,
#245000
1%
#246000
b10110 '
b100000000000000000000 (
03
12
b10000 L
0}
1|
0,!
b1 )!
b0 )!
b0 &!
1*!
0'!
b111 #!
1%!
b101 #!
b100 #!
b100 M
b10111 G
b10101 G
b10100 G
b10100 *
#250000
0%
#251000
b10110 #
b10110 $
b1000000000000000000000 ,
#255000
1%
#256000
b10111 '
b1000000000000000000000 (
02
11
b100000 L
0|
1{
b1 +!
b1 (!
b101 #!
b101 M
b10101 G
b10101 *
#260000
0%
#261000
b10111 #
b10111 $
b10000000000000000000000 ,
#265000
1%
#266000
b11000 '
b10000000000000000000000 (
01
10
b1000000 L
0{
1z
b11 +!
b10 +!
b10 (!
b111 #!
b110 #!
b110 M
b10111 G
b10110 G
b10110 *
#270000
0%
#271000
b11000 #
b11000 $
b100000000000000000000000 ,
#275000
1%
#276000
b11001 '
b100000000000000000000000 (
00
1/
b10000000 L
0z
1y
b11 +!
b11 (!
b111 #!
b111 M
b10111 G
b10111 *
#280000
0%
#281000
b11001 #
b11001 $
b1000000000000000000000000 ,
#285000
1%
#286000
b1100 ,
b1000000000000 (
1:
0/
b0 L
b1000000000000 I
1R
0y
b1 +!
b0 +!
0x
0s
b0 (!
1,!
1'!
b101 #!
b100 #!
b100 o
0p
0d
b100 c
b100 M
b0 #!
1$!
1N
b0 M
b10101 G
b10100 G
b100 _
b1100 _
0`
0K
b1100 J
b10100 *
b100 G
b100 *
b1100 G
b1100 *
#290000
0%
#291000
b11010 #
b11010 $
b11010 '
#295000
1%
#296000
b10110 ,
b10000000000000000000000 (
0:
10
b1000000 L
b0 I
0R
1z
b10 +!
1x
1s
b10 (!
0,!
0'!
b0 o
1p
1d
b0 c
b10 #!
b110 #!
0$!
0N
b110 M
b1000 _
b0 _
1`
1K
b0 J
b1110 G
b11110 G
b10110 G
b10110 *
#300000
0%
#301000
b11011 #
b11011 $
b11011 '
#305000
1%
#306000
b1001 ,
b1000000000 (
b110011011110011110110001 (
1F
1B
1A
1?
1>
1=
1<
19
18
17
16
14
13
1/
b11001101 L
b1110011110110001 I
1^
1Z
1Y
1W
1V
1U
1T
1Q
1P
1O
1"!
1~
1}
1y
b11 +!
b1 )!
b11 )!
0*!
b10 w
0x
b11 w
b10 u
0v
b10 m
b11 m
0n
0l
0g
0i
b11 j
0q
b10 r
0s
b11 t
0%!
b11 &!
b11 (!
b111 #!
b1 o
b101 o
b111 o
0p
b10 e
b11 e
b111 e
0f
0b
b111 a
0d
b111 c
b111 M
b10111 G
b1000 _
b1100 _
b1110 _
b1111 _
0`
0K
b1111 J
b10111 *
#310000
0%
#311000
b11100 #
b11100 $
b11100 '
#315000
1%
#316000
b1000000000 (
0F
0B
0A
0?
0>
0<
09
08
07
06
04
03
00
0/
b0 L
b1000000000 I
0^
0Z
0Y
0W
0V
0T
0Q
0P
0O
0"!
0~
0}
0z
0y
b1 +!
b0 +!
b1 )!
b0 )!
b1 w
b0 w
b0 u
b1 u
b1 m
b0 m
1l
1g
b0 j
1n
b1 r
b0 t
1x
b0 &!
1*!
b0 (!
1,!
1'!
b101 #!
b100 #!
1%!
1s
b101 o
1i
b101 e
b100 e
b100 a
b0 e
1f
b101 c
b1 o
1$!
b100 M
b0 #!
b0 M
b10101 G
b10100 G
1N
b1 c
b1101 _
1b
b0 a
b1101 J
b1001 _
b100 G
b1100 G
b1101 G
b1101 *
b1001 J
b1001 G
b1001 *
#320000
0%
#321000
b11101 #
b11101 $
b11101 '
#325000
1%
#326000
b10011 ,
b10000000000000000000 (
0=
13
b1000 L
b0 I
0U
1}
b10 )!
b11 )!
1v
b0 u
b0 r
1q
b11 &!
0*!
0%!
b10 #!
b11 #!
1p
b0 o
b0 c
1d
b11 M
0$!
0N
b1 _
1`
b0 _
1K
b0 J
b11001 G
b10001 G
b10011 G
b10011 *
#330000
0%
#331000
b11110 #
b11110 $
b11110 '
#335000
1%
#336000
b11 ,
b1000 (
1C
03
b0 L
b1000 I
1[
0}
b1 )!
b0 )!
b10 k
b11 k
b11 h
0l
b0 &!
1*!
1%!
b1 #!
b0 #!
0g
b10 e
b11 e
b11 a
0f
b0 M
1$!
1N
b10001 G
b10000 G
0b
b10 _
b11 _
b11 J
0`
b10000 *
b0 G
1H
1+
b0 *
0K
b10 G
b11 G
b11 *
0H
0+
#340000
0%
#341000
b11111 #
b11111 $
b11111 '
#345000
1%
#346000
b1111 ,
b1000000000000000 (
0C
17
b1000000000000000 I
0[
1O
b10 w
b11 w
b1 k
b0 k
b0 h
1l
b11 t
0x
0s
1g
b1 e
b0 e
b0 a
1f
b1 o
b11 o
b111 o
0p
0d
b111 c
1b
b111 _
b1111 _
b1111 J
b1011 G
b1111 G
b1111 *
#350000
0%
#351000
b100000 #
b100000 $
b100000 '
#355000
1%
#356000
b10000 ,
b10000000000000000 (
b11000011001001111110111 (
1F
1E
1D
1B
1A
1@
1?
1>
1=
1:
16
11
10
b1100001 L
b1001001111110111 I
1^
1]
1\
1Z
1Y
1X
1W
1V
1U
1R
1"!
1{
1z
b10 +!
0,!
0*!
b1 u
0v
b10 m
b11 m
0n
b10 k
0l
0g
b10 h
0i
b11 j
0q
b1 r
0%!
0'!
b10 (!
b10 #!
b110 #!
0$!
b1 e
b101 e
b111 e
0f
0b
b111 a
0N
b110 M
b11111 G
b10111 G
b10110 G
b10110 *
#360000
0%
#361000
b100001 #
b100001 $
b100001 '
#365000
1%
#366000
b101 ,
b100000 (
b11111100011011101001 (
0E
0D
1C
0B
0>
1<
0:
18
15
14
13
01
00
b1111 L
b1100011011101001 I
0]
0\
1[
0Z
0V
1T
0R
1P
1!!
1~
1}
0{
0z
b0 +!
b10 )!
b11 )!
b11 u
b10 u
b11 k
b11 h
b10 r
b11 &!
b0 (!
1,!
1'!
b111 #!
b11 #!
b11 M
b10010 G
b10011 G
b10011 *
#370000
0%
#371000
b100010 #
b100010 $
b100010 '
#375000
1%
#376000
b10001 ,
b100000000000000000 (
0F
0C
0A
0@
0?
0=
0<
08
07
06
04
03
b10 L
b0 I
0^
0[
0Y
0X
0W
0U
0T
0P
0O
0"!
0~
0}
b1 )!
b1 w
b0 w
b0 u
b1 m
b0 m
b1 k
b0 k
b0 h
1l
b0 j
1n
b0 r
1v
b0 t
1x
b1 &!
b1 #!
1s
b101 o
b100 o
1q
1i
b101 e
b100 e
1g
1f
b100 a
b0 e
1p
b100 c
b0 o
b1 M
b10001 G
b0 c
b1101 _
b1100 _
1d
b0 a
1b
1`
b100 _
b100 J
b0 _
b10001 *
b0 J
1K
#380000
0%
#381000
b100011 #
b100011 $
b100011 '
#385000
1%
#386000
b10101 ,
b1000000000000000000000 (
b1110011011110001010111 (
1F
1E
1D
1B
1@
1<
1;
1:
19
17
16
05
13
12
11
b111001 L
b1011110001010111 I
1^
1]
1\
1Z
1X
1T
1S
1R
1Q
1O
1"!
0!!
1}
1|
1{
b1 +!
0,!
b11 )!
b10 w
b11 w
0x
b1 u
b11 u
b10 m
0n
b10 k
0l
0g
b10 h
0i
b10 j
0v
b11 r
0s
b11 t
b11 &!
0'!
b1 (!
b101 #!
b100 o
0p
b110 o
b111 o
0q
b100 e
b110 e
0f
0b
b110 a
0d
b111 c
b101 M
b10101 G
b1 _
b1001 _
b1101 _
b1111 _
0`
0K
b1111 J
b10101 *
#390000
0%
#391000
b100100 #
b100100 $
b100100 '
#395000
1%
