02_rtl/Question2/LOPD_4bit.sv
module LOPD_4bit(
    input logic [3:0]       i_data  ,
    output logic [1:0]      o_pos_one,
    output logic            o_zero_flag
);

/////////////////// LDO ///////////////////
// D[3] | D[2] | D[1] | D[0] |PO[3] | PO[2] | PO[1] | PO[0] | ZERO_FLAG |
//   0  |   0  |   0  |   0  |  0   |   0   |   0   |   0   |     1     |
//   0  |   0  |   0  |   1  |  0   |   0   |   0   |   1   |     0     |
//   0  |   0  |   1  |   X  |  0   |   0   |   1   |   0   |     0     |
//   0  |   1  |   X  |   X  |  0   |   1   |   0   |   0   |     0     |
//   1  |   X  |   X  |   X  |  1   |   0   |   0   |   0   |     0     |
/////////////////// LDOD ///////////////////
// D[3] | D[2] | D[1] | D[0] | PO[1] | PO[0] | ZERO_FLAG |
//   0  |   0  |   0  |   0  |   0   |   0   |     1     |
//   0  |   0  |   0  |   1  |   0   |   0   |     0     |
//   0  |   0  |   1  |   X  |   0   |   1   |     0     |
//   0  |   1  |   X  |   X  |   1   |   0   |     0     |
//   1  |   X  |   X  |   X  |   1   |   1   |     0     |

assign o_zero_flag = ~((o_pos_one[1])|(i_data[1]|i_data[0])) ;
assign o_pos_one[1] = i_data[3] | i_data[2];
assign o_pos_one[0] = ((~(i_data[3] | i_data[2])) & (i_data[1])) |  (i_data[3]);

endmodule

02_rtl/Question2/LOPD_8bit.sv
module LOPD_8bit(
    input logic [7:0]       i_data  ,
    output logic [2:0]      o_pos_one,
    output logic            o_zero_flag
);

////////////////////////////////////////////////////////////
// LOPD_4bit_unit_0
////////////////////////////////////////////////////////////
logic w_zero_flag_0;
logic [1:0] w_pos_one_0;
LOPD_4bit LOPD_4bit_unit_0 (
    .i_data         (i_data[3:0]),
    .o_pos_one      (w_pos_one_0),
    .o_zero_flag    (w_zero_flag_0)
);

////////////////////////////////////////////////////////////
// LOPD_4bit_unit_1
////////////////////////////////////////////////////////////
logic w_zero_flag_1;
logic [1:0] w_pos_one_1;
LOPD_4bit LOPD_4bit_unit_1 (
    .i_data         (i_data[7:4]),
    .o_pos_one      (w_pos_one_1),
    .o_zero_flag    (w_zero_flag_1)
);

////////////////////////////////////////////////////////////
// LOD_8bit_unit
////////////////////////////////////////////////////////////
assign o_zero_flag = w_zero_flag_0 & w_zero_flag_1;
assign o_pos_one[2] = ~(w_zero_flag_1);
assign o_pos_one[1] = (w_zero_flag_1) ? w_pos_one_0[1] : w_pos_one_1[1];
assign o_pos_one[0] = (w_zero_flag_1) ? w_pos_one_0[0] : w_pos_one_1[0];

endmodule

02_rtl/Question2/LOPD_16bit.sv
module LOPD_16bit(
    input logic [15:0]       i_data  ,
    output logic [3:0]      o_pos_one,
    output logic            o_zero_flag
);


////////////////////////////////////////////////////////////
// LOPD_8bit_unit_0
////////////////////////////////////////////////////////////
logic [2:0]         w_pos_one_0;  
logic               w_zero_flag_0;
LOPD_8bit LOPD_8bit_unit_0(
    .i_data         (i_data[7:0]),
    .o_pos_one      (w_pos_one_0),
    .o_zero_flag    (w_zero_flag_0)
);
////////////////////////////////////////////////////////////
// LOPD_8bit_unit_1
////////////////////////////////////////////////////////////
logic [2:0]         w_pos_one_1;  
logic               w_zero_flag_1;
LOPD_8bit LOPD_8bit_unit_1(
    .i_data         (i_data[15:8]),
    .o_pos_one      (w_pos_one_1),
    .o_zero_flag    (w_zero_flag_1)
);

////////////////////////////////////////////////////////////
// LOD_16bit_unit
////////////////////////////////////////////////////////////
assign o_zero_flag = w_zero_flag_0 & w_zero_flag_1;
assign o_pos_one[3] = ~(w_zero_flag_1);
assign o_pos_one[2] = w_zero_flag_1 ? w_pos_one_0[2] : w_pos_one_1[2];
assign o_pos_one[1] = w_zero_flag_1 ? w_pos_one_0[1] : w_pos_one_1[1];
assign o_pos_one[0] = w_zero_flag_1 ? w_pos_one_0[0] : w_pos_one_1[0];
endmodule

02_rtl/Question2/Question2.sv
module Question2 #(
    parameter SIZE_DATA     = 24    ,
    parameter SIZE_LOPD     = 5      
)(
    input logic [SIZE_DATA-1:0]     i_data          ,
    output logic [SIZE_LOPD-1:0]    o_one_position  ,
    output logic                    o_zero_flag      
);

logic [15:0]     LOPD16_i_data;
assign LOPD16_i_data = i_data[15:0];
logic [3:0]      LOPD16_o_pos_one;
logic            LOPD16_o_zero_flag;
logic [7:0]      LOPD8_i_data;
assign LOPD8_i_data = i_data[23:16];
logic [2:0]      LOPD8_o_pos_one;
logic            LOPD8_o_zero_flag;
LOPD_16bit LOPD_16bit_UNIT_LSB (
    .i_data             (LOPD16_i_data),
    .o_pos_one          (LOPD16_o_pos_one),
    .o_zero_flag        (LOPD16_o_zero_flag)
);

LOPD_8bit LOPD_8bit_UNIT_MSB (
    .i_data             (LOPD8_i_data),
    .o_pos_one          (LOPD8_o_pos_one),
    .o_zero_flag        (LOPD8_o_zero_flag)
);

assign o_zero_flag = LOPD16_o_zero_flag & LOPD8_o_zero_flag;
assign o_one_position[0] = LOPD8_o_zero_flag ? LOPD16_o_pos_one[0] : LOPD8_o_pos_one[0];
assign o_one_position[1] = LOPD8_o_zero_flag ? LOPD16_o_pos_one[1] : LOPD8_o_pos_one[1];
assign o_one_position[2] = LOPD8_o_zero_flag ? LOPD16_o_pos_one[2] : LOPD8_o_pos_one[2];
assign o_one_position[3] = LOPD8_o_zero_flag ? LOPD16_o_pos_one[3] : 1'b0;
assign o_one_position[4] = ~LOPD8_o_zero_flag;

endmodule

03_test/Question2/tb_Question2.sv
`timescale 1ns/1ps
module tb_Question2();

parameter SIZE_DATA = 24;
parameter SIZE_LOP  = 5;

int test_count = 0;
int test_pass  = 0;

logic i_clk, i_rst_n;
logic [SIZE_DATA-1:0] i_addr;
logic [SIZE_DATA-1:0] i_data;
logic [SIZE_DATA-1:0] o_addr;  
logic [SIZE_LOP-1:0]  o_one_position;
logic                 o_zero_flag;

function automatic logic [SIZE_LOP-1:0] Test_LOPD(
    input logic [SIZE_DATA-1:0]     f_i_data
);
    logic [SIZE_DATA-1:0] t_temp;
    int cnt_position_1;
    begin
        t_temp = f_i_data;
        cnt_position_1 = 0;

        if(t_temp == 0) begin
            Test_LOPD = '0;
        end else begin
            while (t_temp[SIZE_DATA-1] == 0) begin
                t_temp = t_temp << 1;
                cnt_position_1 ++;
            end
            Test_LOPD = SIZE_DATA - cnt_position_1 - 1;
        end
    end

endfunction

//===================== DUT =====================//

Question2 #(
    .SIZE_DATA (SIZE_DATA),
    .SIZE_LOPD  (SIZE_LOP)
) DUT (
    .i_data         (i_data),
    .o_one_position (o_one_position),
    .o_zero_flag    (o_zero_flag)
);

//===================== CLOCK =====================//
initial begin
    i_clk = 0;
    forever #5 i_clk = ~i_clk; // 10ns period = 100MHz
end

//===================== DUMP WAVE =====================//
// initial begin
//     $dumpfile("tb_Question2.vcd");
//     $dumpvars(0, tb_Question2);
// end
//===================== TEST SEQUENCE =====================//
int bit_pos;
initial begin
    i_rst_n = 0;
    i_addr  = '0;
    i_data  = '0;

    // Reset phase
    #20;
    i_rst_n = 1;
    #10;

    repeat (1) begin
        @(posedge i_clk);
        #1;
        i_addr = i_addr + 1;
        i_data  = 24'b0;
        @(negedge i_clk);
        #1;
        $display("[TIME: %5t] [%s] i_data = %b (%d) \t| o_one_position = %b (%d) \t| o_zero_flag = %b", $time, "Zero", i_data, i_data, o_one_position, o_one_position, o_zero_flag);
        $display("=> %4s: Expect: %8h, DUT: %8h ", (Test_LOPD(i_data) == o_one_position) ? "PASS" : "FAIL", o_one_position, Test_LOPD(i_data));
        test_count = test_count + 1;
        test_pass  = (Test_LOPD(i_data) == o_one_position) ? test_pass + 1 : test_pass;
    end

    bit_pos = 1;
    repeat (24) begin
        @(posedge i_clk);
        #1;
        i_addr = i_addr + 1;
        i_data  = bit_pos;
        @(negedge i_clk);
        #1;
        $display("[TIME: %5t] [%s] i_data = %b (%d) \t| o_one_position = %b (%d) \t| o_zero_flag = %b", $time, "Direcly", i_data, i_data, o_one_position, o_one_position, o_zero_flag);
        $display("=> %4s: Expect: %8h, DUT: %8h ", (Test_LOPD(i_data) == o_one_position) ? "PASS" : "FAIL", o_one_position, Test_LOPD(i_data));
        test_count = test_count + 1;
        test_pass  = (Test_LOPD(i_data) == o_one_position) ? test_pass + 1 : test_pass;
        bit_pos = bit_pos << 1'b1;
    end
    repeat (100) begin
        @(posedge i_clk);
        #1;
        bit_pos = $urandom_range(0, SIZE_DATA-1);
        i_data = 24'b1 << bit_pos;
        if ($urandom_range(0, 1)) begin
            i_data |= $urandom_range(0, (1 << SIZE_DATA) - 1);
        end
        #5;
        $display("[TIME: %5t] [%s] i_data = %b (%d) \t| o_one_position = %b (%d) \t| o_zero_flag = %b", $time, "Random", i_data, i_data, o_one_position, o_one_position, o_zero_flag);
        $display("=> %4s: Expect: %8h, DUT: %8h ", (Test_LOPD(i_data) == o_one_position) ? "PASS" : "FAIL", o_one_position, Test_LOPD(i_data));
        test_count = test_count + 1;
        test_pass  = (Test_LOPD(i_data) == o_one_position) ? test_pass + 1 : test_pass;
        i_addr = i_addr + 1;
    end

    #10;
    $display("\n================================");
    $display("==========TEST SUMMARY==========");
    $display("Total test cases: %6d    ", test_count);
    $display("Passed          : %6d    ", test_pass);
    $display("Failed          : %6d    ", test_count - test_pass);
    $display("Pass rate       : %0.2f%%", (test_pass * 100.0) / (test_count));
    $display("================================");
    #100;

    $finish;
end

endmodule

03_test/Question2/Verilator/tb_Question2.vcd
$version Generated by VerilatedVcd $end
$timescale 1ps $end
 $scope module TOP $end
  $scope module tb_Question2 $end
   $var wire 32 J SIZE_DATA [31:0] $end
   $var wire 32 K SIZE_LOP [31:0] $end
   $var wire 32 # test_count [31:0] $end
   $var wire 32 $ test_pass [31:0] $end
   $var wire 1 E i_clk $end
   $var wire 1 % i_rst_n $end
   $var wire 24 & i_addr [23:0] $end
   $var wire 24 ' i_data [23:0] $end
   $var wire 24 L o_addr [23:0] $end
   $var wire 5 3 o_one_position [4:0] $end
   $var wire 1 4 o_zero_flag $end
   $var wire 32 ( bit_pos [31:0] $end
   $scope module DUT $end
    $var wire 32 J SIZE_DATA [31:0] $end
    $var wire 32 K SIZE_LOPD [31:0] $end
    $var wire 24 ' i_data [23:0] $end
    $var wire 5 3 o_one_position [4:0] $end
    $var wire 1 4 o_zero_flag $end
    $var wire 16 ) LOPD16_i_data [15:0] $end
    $var wire 4 5 LOPD16_o_pos_one [3:0] $end
    $var wire 1 6 LOPD16_o_zero_flag $end
    $var wire 8 * LOPD8_i_data [7:0] $end
    $var wire 3 7 LOPD8_o_pos_one [2:0] $end
    $var wire 1 8 LOPD8_o_zero_flag $end
    $scope module LOPD_16bit_UNIT_LSB $end
     $var wire 16 ) i_data [15:0] $end
     $var wire 4 5 o_pos_one [3:0] $end
     $var wire 1 6 o_zero_flag $end
     $var wire 3 9 w_pos_one_0 [2:0] $end
     $var wire 1 : w_zero_flag_0 $end
     $var wire 3 ; w_pos_one_1 [2:0] $end
     $var wire 1 F w_zero_flag_1 $end
     $scope module LOPD_8bit_unit_0 $end
      $var wire 8 + i_data [7:0] $end
      $var wire 3 9 o_pos_one [2:0] $end
      $var wire 1 : o_zero_flag $end
      $var wire 1 < w_zero_flag_0 $end
      $var wire 2 = w_pos_one_0 [1:0] $end
      $var wire 1 G w_zero_flag_1 $end
      $var wire 2 > w_pos_one_1 [1:0] $end
      $scope module LOPD_4bit_unit_0 $end
       $var wire 4 , i_data [3:0] $end
       $var wire 2 = o_pos_one [1:0] $end
       $var wire 1 < o_zero_flag $end
      $upscope $end
      $scope module LOPD_4bit_unit_1 $end
       $var wire 4 - i_data [3:0] $end
       $var wire 2 > o_pos_one [1:0] $end
       $var wire 1 G o_zero_flag $end
      $upscope $end
     $upscope $end
     $scope module LOPD_8bit_unit_1 $end
      $var wire 8 . i_data [7:0] $end
      $var wire 3 ; o_pos_one [2:0] $end
      $var wire 1 F o_zero_flag $end
      $var wire 1 ? w_zero_flag_0 $end
      $var wire 2 @ w_pos_one_0 [1:0] $end
      $var wire 1 H w_zero_flag_1 $end
      $var wire 2 A w_pos_one_1 [1:0] $end
      $scope module LOPD_4bit_unit_0 $end
       $var wire 4 / i_data [3:0] $end
       $var wire 2 @ o_pos_one [1:0] $end
       $var wire 1 ? o_zero_flag $end
      $upscope $end
      $scope module LOPD_4bit_unit_1 $end
       $var wire 4 0 i_data [3:0] $end
       $var wire 2 A o_pos_one [1:0] $end
       $var wire 1 H o_zero_flag $end
      $upscope $end
     $upscope $end
    $upscope $end
    $scope module LOPD_8bit_UNIT_MSB $end
     $var wire 8 * i_data [7:0] $end
     $var wire 3 7 o_pos_one [2:0] $end
     $var wire 1 8 o_zero_flag $end
     $var wire 1 B w_zero_flag_0 $end
     $var wire 2 C w_pos_one_0 [1:0] $end
     $var wire 1 I w_zero_flag_1 $end
     $var wire 2 D w_pos_one_1 [1:0] $end
     $scope module LOPD_4bit_unit_0 $end
      $var wire 4 1 i_data [3:0] $end
      $var wire 2 C o_pos_one [1:0] $end
      $var wire 1 B o_zero_flag $end
     $upscope $end
     $scope module LOPD_4bit_unit_1 $end
      $var wire 4 2 i_data [3:0] $end
      $var wire 2 D o_pos_one [1:0] $end
      $var wire 1 I o_zero_flag $end
     $upscope $end
    $upscope $end
   $upscope $end
  $upscope $end
 $upscope $end
$enddefinitions $end


#0
b00000000000000000000000000000000 #
b00000000000000000000000000000000 $
0%
b000000000000000000000000 &
b000000000000000000000000 '
b00000000000000000000000000000000 (
b0000000000000000 )
b00000000 *
b00000000 +
b0000 ,
b0000 -
b00000000 .
b0000 /
b0000 0
b0000 1
b0000 2
b00000 3
14
b0000 5
16
b000 7
18
b000 9
1:
b000 ;
1<
b00 =
b00 >
1?
b00 @
b00 A
1B
b00 C
b00 D
0E
1F
1G
1H
1I
b00000000000000000000000000011000 J
b00000000000000000000000000000101 K
b000000000000000000000000 L
#5000
1E
#10000
0E
#15000
1E
#20000
1%
0E
#25000
1E
#30000
0E
#35000
1E
#36000
b000000000000000000000001 &
#40000
0E
#41000
b00000000000000000000000000000001 #
b00000000000000000000000000000001 $
b00000000000000000000000000000001 (
#45000
1E
#46000
b000000000000000000000010 &
b000000000000000000000001 '
b0000000000000001 )
b00000001 +
b0001 ,
04
06
0:
0<
#50000
0E
#51000
b00000000000000000000000000000010 #
b00000000000000000000000000000010 $
b00000000000000000000000000000010 (
#55000
1E
#56000
b000000000000000000000011 &
b000000000000000000000010 '
b0000000000000010 )
b00000010 +
b0010 ,
b00001 3
b0001 5
b001 9
b01 =
#60000
0E
#61000
b00000000000000000000000000000011 #
b00000000000000000000000000000011 $
b00000000000000000000000000000100 (
#65000
1E
#66000
b000000000000000000000100 &
b000000000000000000000100 '
b0000000000000100 )
b00000100 +
b0100 ,
b00010 3
b0010 5
b010 9
b10 =
#70000
0E
#71000
b00000000000000000000000000000100 #
b00000000000000000000000000000100 $
b00000000000000000000000000001000 (
#75000
1E
#76000
b000000000000000000000101 &
b000000000000000000001000 '
b0000000000001000 )
b00001000 +
b1000 ,
b00011 3
b0011 5
b011 9
b11 =
#80000
0E
#81000
b00000000000000000000000000000101 #
b00000000000000000000000000000101 $
b00000000000000000000000000010000 (
#85000
1E
#86000
b000000000000000000000110 &
b000000000000000000010000 '
b0000000000010000 )
b00010000 +
b0000 ,
b0001 -
b00100 3
b0100 5
b100 9
1<
b00 =
0G
#90000
0E
#91000
b00000000000000000000000000000110 #
b00000000000000000000000000000110 $
b00000000000000000000000000100000 (
#95000
1E
#96000
b000000000000000000000111 &
b000000000000000000100000 '
b0000000000100000 )
b00100000 +
b0010 -
b00101 3
b0101 5
b101 9
b01 >
#100000
0E
#101000
b00000000000000000000000000000111 #
b00000000000000000000000000000111 $
b00000000000000000000000001000000 (
#105000
1E
#106000
b000000000000000000001000 &
b000000000000000001000000 '
b0000000001000000 )
b01000000 +
b0100 -
b00110 3
b0110 5
b110 9
b10 >
#110000
0E
#111000
b00000000000000000000000000001000 #
b00000000000000000000000000001000 $
b00000000000000000000000010000000 (
#115000
1E
#116000
b000000000000000000001001 &
b000000000000000010000000 '
b0000000010000000 )
b10000000 +
b1000 -
b00111 3
b0111 5
b111 9
b11 >
#120000
0E
#121000
b00000000000000000000000000001001 #
b00000000000000000000000000001001 $
b00000000000000000000000100000000 (
#125000
1E
#126000
b000000000000000000001010 &
b000000000000000100000000 '
b0000000100000000 )
b00000000 +
b0000 -
b00000001 .
b0001 /
b01000 3
b1000 5
b000 9
1:
b00 >
0?
0F
1G
#130000
0E
#131000
b00000000000000000000000000001010 #
b00000000000000000000000000001010 $
b00000000000000000000001000000000 (
#135000
1E
#136000
b000000000000000000001011 &
b000000000000001000000000 '
b0000001000000000 )
b00000010 .
b0010 /
b01001 3
b1001 5
b001 ;
b01 @
#140000
0E
#141000
b00000000000000000000000000001011 #
b00000000000000000000000000001011 $
b00000000000000000000010000000000 (
#145000
1E
#146000
b000000000000000000001100 &
b000000000000010000000000 '
b0000010000000000 )
b00000100 .
b0100 /
b01010 3
b1010 5
b010 ;
b10 @
#150000
0E
#151000
b00000000000000000000000000001100 #
b00000000000000000000000000001100 $
b00000000000000000000100000000000 (
#155000
1E
#156000
b000000000000000000001101 &
b000000000000100000000000 '
b0000100000000000 )
b00001000 .
b1000 /
b01011 3
b1011 5
b011 ;
b11 @
#160000
0E
#161000
b00000000000000000000000000001101 #
b00000000000000000000000000001101 $
b00000000000000000001000000000000 (
#165000
1E
#166000
b000000000000000000001110 &
b000000000001000000000000 '
b0001000000000000 )
b00010000 .
b0000 /
b0001 0
b01100 3
b1100 5
b100 ;
1?
b00 @
0H
#170000
0E
#171000
b00000000000000000000000000001110 #
b00000000000000000000000000001110 $
b00000000000000000010000000000000 (
#175000
1E
#176000
b000000000000000000001111 &
b000000000010000000000000 '
b0010000000000000 )
b00100000 .
b0010 0
b01101 3
b1101 5
b101 ;
b01 A
#180000
0E
#181000
b00000000000000000000000000001111 #
b00000000000000000000000000001111 $
b00000000000000000100000000000000 (
#185000
1E
#186000
b000000000000000000010000 &
b000000000100000000000000 '
b0100000000000000 )
b01000000 .
b0100 0
b01110 3
b1110 5
b110 ;
b10 A
#190000
0E
#191000
b00000000000000000000000000010000 #
b00000000000000000000000000010000 $
b00000000000000001000000000000000 (
#195000
1E
#196000
b000000000000000000010001 &
b000000001000000000000000 '
b1000000000000000 )
b10000000 .
b1000 0
b01111 3
b1111 5
b111 ;
b11 A
#200000
0E
#201000
b00000000000000000000000000010001 #
b00000000000000000000000000010001 $
b00000000000000010000000000000000 (
#205000
1E
#206000
b000000000000000000010010 &
b000000010000000000000000 '
b0000000000000000 )
b00000001 *
b00000000 .
b0000 0
b0001 1
b10000 3
b0000 5
16
08
b000 ;
b00 A
0B
1F
1H
#210000
0E
#211000
b00000000000000000000000000010010 #
b00000000000000000000000000010010 $
b00000000000000100000000000000000 (
#215000
1E
#216000
b000000000000000000010011 &
b000000100000000000000000 '
b00000010 *
b0010 1
b10001 3
b001 7
b01 C
#220000
0E
#221000
b00000000000000000000000000010011 #
b00000000000000000000000000010011 $
b00000000000001000000000000000000 (
#225000
1E
#226000
b000000000000000000010100 &
b000001000000000000000000 '
b00000100 *
b0100 1
b10010 3
b010 7
b10 C
#230000
0E
#231000
b00000000000000000000000000010100 #
b00000000000000000000000000010100 $
b00000000000010000000000000000000 (
#235000
1E
#236000
b000000000000000000010101 &
b000010000000000000000000 '
b00001000 *
b1000 1
b10011 3
b011 7
b11 C
#240000
0E
#241000
b00000000000000000000000000010101 #
b00000000000000000000000000010101 $
b00000000000100000000000000000000 (
#245000
1E
#246000
b000000000000000000010110 &
b000100000000000000000000 '
b00010000 *
b0000 1
b0001 2
b10100 3
b100 7
1B
b00 C
0I
#250000
0E
#251000
b00000000000000000000000000010110 #
b00000000000000000000000000010110 $
b00000000001000000000000000000000 (
#255000
1E
#256000
b000000000000000000010111 &
b001000000000000000000000 '
b00100000 *
b0010 2
b10101 3
b101 7
b01 D
#260000
0E
#261000
b00000000000000000000000000010111 #
b00000000000000000000000000010111 $
b00000000010000000000000000000000 (
#265000
1E
#266000
b000000000000000000011000 &
b010000000000000000000000 '
b01000000 *
b0100 2
b10110 3
b110 7
b10 D
#270000
0E
#271000
b00000000000000000000000000011000 #
b00000000000000000000000000011000 $
b00000000100000000000000000000000 (
#275000
1E
#276000
b000000000000000000011001 &
b100000000000000000000000 '
b10000000 *
b1000 2
b10111 3
b111 7
b11 D
#280000
0E
#281000
b00000000000000000000000000011001 #
b00000000000000000000000000011001 $
b00000001000000000000000000000000 (
#285000
1E
#286000
b000100000000000000000000 '
b00000000000000000000000000010100 (
b00010000 *
b0001 2
b10100 3
b100 7
b00 D
#290000
0E
#291000
b00000000000000000000000000011010 #
b00000000000000000000000000011010 $
b000000000000000000011010 &
#295000
1E
#296000
b000000000000000000000100 '
b00000000000000000000000000000010 (
b0000000000000100 )
b00000000 *
b00000100 +
b0100 ,
b0000 2
b00010 3
b0010 5
06
b000 7
18
b010 9
0:
0<
b10 =
1I
#300000
0E
#301000
b00000000000000000000000000011011 #
b00000000000000000000000000011011 $
b000000000000000000011011 &
#305000
1E
#306000
b000000000000000000000001 '
b00000000000000000000000000000000 (
b0000000000000001 )
b00000001 +
b0001 ,
b00000 3
b0000 5
b000 9
b00 =
#310000
0E
#311000
b00000000000000000000000000011100 #
b00000000000000000000000000011100 $
b000000000000000000011100 &
#315000
1E
#316000
b010000000000000000000000 '
b00000000000000000000000000010110 (
b0000000000000000 )
b01000000 *
b00000000 +
b0000 ,
b0100 2
b10110 3
16
b110 7
08
1:
1<
b10 D
0I
#320000
0E
#321000
b00000000000000000000000000011101 #
b00000000000000000000000000011101 $
b000000000000000000011101 &
#325000
1E
#326000
b100111100001011110100001 '
b00000000000000000000000000000111 (
b0001011110100001 )
b10011110 *
b10100001 +
b0001 ,
b1010 -
b00010111 .
b0111 /
b0001 0
b1110 1
b1001 2
b10111 3
b1100 5
06
b111 7
b111 9
0:
b100 ;
0<
b11 >
0?
b10 @
0B
b11 C
b11 D
0F
0G
0H
#330000
0E
#331000
b00000000000000000000000000011110 #
b00000000000000000000000000011110 $
b000000000000000000011110 &
#335000
1E
#336000
b010100111111001110000010 '
b00000000000000000000000000010001 (
b1111001110000010 )
b01010011 *
b10000010 +
b0010 ,
b1000 -
b11110011 .
b0011 /
b1111 0
b0011 1
b0101 2
b10110 3
b1111 5
b110 7
b111 ;
b01 =
b01 @
b11 A
b01 C
b10 D
#340000
0E
#341000
b00000000000000000000000000011111 #
b00000000000000000000000000011111 $
b000000000000000000011111 &
#345000
1E
#346000
b111110111100110100010010 '
b00000000000000000000000000001010 (
b1100110100010010 )
b11111011 *
b00010010 +
b0001 -
b11001101 .
b1101 /
b1100 0
b1011 1
b1111 2
b10111 3
b111 7
b100 9
b00 >
b11 @
b11 C
b11 D
#350000
0E
#351000
b00000000000000000000000000100000 #
b00000000000000000000000000100000 $
b000000000000000000100000 &
#355000
1E
#356000
b011010110100000111110100 '
b00000000000000000000000000001110 (
b0100000111110100 )
b01101011 *
b11110100 +
b0100 ,
b1111 -
b01000001 .
b0001 /
b0100 0
b0110 2
b10110 3
b1110 5
b110 7
b111 9
b110 ;
b10 =
b11 >
b00 @
b10 A
b10 D
#360000
0E
#361000
b00000000000000000000000000100001 #
b00000000000000000000000000100001 $
b000000000000000000100001 &
#365000
1E
#366000
b000000000000100000000000 '
b00000000000000000000000000001011 (
b0000100000000000 )
b00000000 *
b00000000 +
b0000 ,
b0000 -
b00001000 .
b1000 /
b0000 0
b0000 1
b0000 2
b01011 3
b1011 5
b000 7
18
b000 9
1:
b011 ;
1<
b00 =
b00 >
b11 @
b00 A
1B
b00 C
b00 D
1G
1H
1I
#370000
0E
#371000
b00000000000000000000000000100010 #
b00000000000000000000000000100010 $
b000000000000000000100010 &
#375000
1E
#376000
b000000000000000000000100 '
b00000000000000000000000000000010 (
b0000000000000100 )
b00000100 +
b0100 ,
b00000000 .
b0000 /
b00010 3
b0010 5
b010 9
0:
b000 ;
0<
b10 =
1?
b00 @
1F
#380000
0E
#381000
b00000000000000000000000000100011 #
b00000000000000000000000000100011 $
b000000000000000000100011 &
#385000
1E
#386000
b000000000000000001000000 '
b00000000000000000000000000000110 (
b0000000001000000 )
b01000000 +
b0000 ,
b0100 -
b00110 3
b0110 5
b110 9
1<
b00 =
b10 >
0G
#390000
0E
#391000
b00000000000000000000000000100100 #
b00000000000000000000000000100100 $
b000000000000000000100100 &
#395000
1E
#396000
#400000
0E
#401000
b00000000000000000000000000100101 #
b00000000000000000000000000100101 $
b000000000000000000100101 &
#405000
1E
#406000
b000000010000000000000000 '
b00000000000000000000000000010000 (
b0000000000000000 )
b00000001 *
b00000000 +
b0000 -
b0001 1
b10000 3
b0000 5
16
08
b000 9
1:
b00 >
0B
1G
#410000
0E
#411000
b00000000000000000000000000100110 #
b00000000000000000000000000100110 $
b000000000000000000100110 &
#415000
1E
#416000
b000000000000000000001000 '
b00000000000000000000000000000011 (
b0000000000001000 )
b00000000 *
b00001000 +
b1000 ,
b0000 1
b00011 3
b0011 5
06
18
b011 9
0:
0<
b11 =
1B
#420000
0E
#421000
b00000000000000000000000000100111 #
b00000000000000000000000000100111 $
b000000000000000000100111 &
#425000
1E
#426000
b000000000010000000000000 '
b00000000000000000000000000001101 (
b0010000000000000 )
b00000000 +
b0000 ,
b00100000 .
b0010 0
b01101 3
b1101 5
b000 9
1:
b101 ;
1<
b00 =
b01 A
0F
0H
#430000
0E
#431000
b00000000000000000000000000101000 #
b00000000000000000000000000101000 $
b000000000000000000101000 &
#435000
1E
#436000
b011011010011001001100011 '
b00000000000000000000000000010110 (
b0011001001100011 )
b01101101 *
b01100011 +
b0011 ,
b0110 -
b00110010 .
b0010 /
b0011 0
b1101 1
b0110 2
b10110 3
b110 7
08
b110 9
0:
0<
b01 =
b10 >
0?
b01 @
0B
b11 C
b10 D
0G
0I
#440000
0E
#441000
b00000000000000000000000000101001 #
b00000000000000000000000000101001 $
b000000000000000000101001 &
#445000
1E
#446000
b010101011101101011001110 '
b00000000000000000000000000010000 (
b1101101011001110 )
b01010101 *
b11001110 +
b1110 ,
b1100 -
b11011010 .
b1010 /
b1101 0
b0101 1
b0101 2
b1111 5
b111 9
b111 ;
b11 =
b11 >
b11 @
b11 A
b10 C
#450000
0E
#451000
b00000000000000000000000000101010 #
b00000000000000000000000000101010 $
b000000000000000000101010 &
#455000
1E
#456000
b110110011011001110011110 '
b00000000000000000000000000001111 (
b1011001110011110 )
b11011001 *
b10011110 +
b1001 -
b10110011 .
b0011 /
b1011 0
b1001 1
b1101 2
b10111 3
b111 7
b01 @
b11 C
b11 D
#460000
0E
#461000
b00000000000000000000000000101011 #
b00000000000000000000000000101011 $
b000000000000000000101011 &
#465000
1E
#466000
b000000001000000000000000 '
b1000000000000000 )
b00000000 *
b00000000 +
b0000 ,
b0000 -
b10000000 .
b0000 /
b1000 0
b0000 1
b0000 2
b01111 3
b000 7
18
b000 9
1:
1<
b00 =
b00 >
1?
b00 @
1B
b00 C
b00 D
1G
1I
#470000
0E
#471000
b00000000000000000000000000101100 #
b00000000000000000000000000101100 $
b000000000000000000101100 &
#475000
1E
#476000
b111100111001000010111011 '
b00000000000000000000000000010000 (
b1001000010111011 )
b11110011 *
b10111011 +
b1011 ,
b1011 -
b10010000 .
b1001 0
b0011 1
b1111 2
b10111 3
b111 7
08
b111 9
0:
0<
b11 =
b11 >
0B
b01 C
b11 D
0G
0I
#480000
0E
#481000
b00000000000000000000000000101101 #
b00000000000000000000000000101101 $
b000000000000000000101101 &
#485000
1E
#486000
b000100000000000000000000 '
b00000000000000000000000000010100 (
b0000000000000000 )
b00010000 *
b00000000 +
b0000 ,
b0000 -
b00000000 .
b0000 0
b0000 1
b0001 2
b10100 3
b0000 5
16
b100 7
b000 9
1:
b000 ;
1<
b00 =
b00 >
b00 A
1B
b00 C
b00 D
1F
1G
1H
#490000
0E
#491000
b00000000000000000000000000101110 #
b00000000000000000000000000101110 $
b000000000000000000101110 &
#495000
1E
#496000
b010101001011001101001001 '
b00000000000000000000000000000110 (
b1011001101001001 )
b01010100 *
b01001001 +
b1001 ,
b0100 -
b10110011 .
b0011 /
b1011 0
b0100 1
b0101 2
b10110 3
b1111 5
06
b110 7
b110 9
0:
b111 ;
0<
b11 =
b10 >
0?
b01 @
b11 A
0B
b10 C
b10 D
0F
0G
0H
#500000
0E
#501000
b00000000000000000000000000101111 #
b00000000000000000000000000101111 $
b000000000000000000101111 &
#505000
1E
#506000
b101011011010111110001100 '
b00000000000000000000000000000011 (
b1010111110001100 )
b10101101 *
b10001100 +
b1100 ,
b1000 -
b10101111 .
b1111 /
b1010 0
b1101 1
b1010 2
b10111 3
b111 7
b111 9
b11 >
b11 @
b11 C
b11 D
#510000
0E
#511000
b00000000000000000000000000110000 #
b00000000000000000000000000110000 $
b000000000000000000110000 &
#515000
1E
#516000
b011100101110101001101011 '
b00000000000000000000000000000101 (
b1110101001101011 )
b01110010 *
b01101011 +
b1011 ,
b0110 -
b11101010 .
b1010 /
b1110 0
b0010 1
b0111 2
b10110 3
b110 7
b110 9
b10 >
b01 C
b10 D
#520000
0E
#521000
b00000000000000000000000000110001 #
b00000000000000000000000000110001 $
b000000000000000000110001 &
#525000
1E
#526000
b101100110010110011001001 '
b00000000000000000000000000010100 (
b0010110011001001 )
b10110011 *
b11001001 +
b1001 ,
b1100 -
b00101100 .
b1100 /
b0010 0
b0011 1
b1011 2
b10111 3
b1101 5
b111 7
b111 9
b101 ;
b11 >
b01 A
b11 D
#530000
0E
#531000
b00000000000000000000000000110010 #
b00000000000000000000000000110010 $
b000000000000000000110010 &
#535000
1E
