20_doc/my-chapters/my-ref/verify/verify/c5/code/cla_4bit.sv
module cla_4bit (
    input  logic [3:0]A,
	 input  logic [3:0]B,
	 input  logic cin,
	 output logic cout,Pblk,Gblk,
	 output logic [3:0]sum
);
   logic [3:0]g,p;
   assign  g = A & B;
	assign  p = A ^ B;
	
	logic  c1,c2,c3;
	assign c1   = g[0] | (p[0]&cin);
   assign c2   = g[1] | (g[0]&p[1]) | (p[1]&p[0]&cin);
   assign c3   = g[2] | (g[1]&p[2]) | (g[0]&p[2]&p[1]) | (p[2]&p[1]&p[0]&cin);
	assign cout = g[3] | (g[2]&p[3]) | (g[1]&p[3]&p[2]) | (g[0]&p[3]&p[2]&p[1]) | (p[3]&p[2]&p[1]&p[0]&cin); 
   
	assign sum[0] = p[0]^cin;
   assign sum[1] = p[1]^c1; 
   assign sum[2] = p[2]^c2;
   assign sum[3] = p[3]^c3;
	assign Pblk   = p[3]&p[2]&p[1]&p[0];
	assign Gblk   = g[3] | (g[2]&p[3]) | (g[1]&p[3]&p[2]) | (g[0]&p[3]&p[2]&p[1]); 
	
	endmodule

02_rtl/Question5/cla_8bit.sv
module cla_8bit (
    input  logic [7:0] A,
    input  logic [7:0] B,
    input  logic        Cin,
    output logic [7:0] Sum,
    output logic        Cout
);
    logic [1:0] Gblk, Pblk;
    logic [2:0] Cblk;   
    assign Cblk[0] = Cin;

    genvar i;
    generate
        for (i = 0; i < 2; i = i + 1) begin : BLK
            cla_4bit u4 (
                .A   (A[4*i +: 4]),
                .B   (B[4*i +: 4]),
                .cin (Cblk[i]),
                .sum (Sum[4*i +: 4]),
                .cout(),
                .Gblk(Gblk[i]),
                .Pblk(Pblk[i])
            );
        
            assign Cblk[i+1] = Gblk[i] | (Pblk[i] & Cblk[i]);
        end
    endgenerate

    assign Cout = Cblk[2];
endmodule

03_test/Question5/Verilator/coverage/annotated_src/alu_8bit.sv
//      // verilator_coverage annotation
        module alu_8bit (
%000004     input  logic [7:0] A,
%000004     input  logic [7:0] B,
 000035     input  logic       S1,
 000070     input  logic       S0,
 000056     input  logic       Cin,
 000041     output logic [7:0] F,
 000040     output logic       Cout
        );
            
%000005     logic [7:0] B_comp;
            assign      B_comp = ~B;
        
 000035     logic  sel_op1; 
            assign sel_op1 = S1 & (~S0);
        
 000023     logic [7:0] Op1;
        
            genvar i;
            generate
                for (i = 0; i < 8; i = i + 1) begin : OP1_MUX
                    assign Op1[i] = sel_op1 ? B_comp[i] : A[i];
                end
            endgenerate
        
 000018     logic [7:0] Op2;
%000001     always_comb begin
%000001         case ({S1, S0})
 000073             2'b00: Op2 = B;
 000072             2'b01: Op2 = 8'b0;
 000074             2'b10: Op2 = 8'b0;
 000068             2'b11: Op2 = B_comp;
%000000             default: Op2 = 8'b0;
                endcase
            end
        
            cla_8bit u_adder (
                .A   (Op1),
                .B   (Op2),
                .Cin (Cin),
                .Sum (F),
                .Cout(Cout)
            );
        
        endmodule

03_test/Question5/tb_Question5.sv
`timescale 1ns/1ps

module tb_Question5;
    // ==============================
    // DUT signals
    // ==============================
    logic [7:0] A, B;
    logic S1, S0, Cin;
    logic [7:0] F;
    logic Cout;

    // ==============================
    // Instantiate DUT 
    // ==============================
    alu_8bit dut (
        .A(A), .B(B), .S1(S1), .S0(S0), .Cin(Cin),
        .F(F), .Cout(Cout)
    );

    // ==============================
    // Test control / statistics
    // ==============================
    integer total_tests;
    integer errors;
    integer test_count;
    integer test_pass;
    int unsigned seed;

    // ==============================
    // Waveform dump 
    // ==============================
    initial begin
        $dumpfile("tb_Question5.vcd");
        $dumpvars(0, tb_Question5);
    end
    // initial begin
    //     $shm_open("waves.shm");
    //     $shm_probe("ASM");
    // end

    // ==============================
    // Reference model 
    // ==============================
    function automatic int unsigned ref_model(
        input logic [7:0] A_i,
        input logic [7:0] B_i,
        input logic S1_i,
        input logic S0_i,
        input logic Cin_i
    );
        logic [7:0] B_comp;
        logic [7:0] Op1, Op2;
        int unsigned sum9;
    begin
        B_comp = ~B_i;

        // Op1 selection
        if (S1_i && !S0_i)
            Op1 = B_comp;
        else
            Op1 = A_i;

        // Op2 selection per {S1,S0}
        case ({S1_i, S0_i})
            2'b00: Op2 = B_i;
            2'b01: Op2 = 8'h00;
            2'b10: Op2 = 8'h00;
            2'b11: Op2 = B_comp;
            default: Op2 = 8'h00;
        endcase

        sum9 = Op1 + Op2 + (Cin_i ? 1 : 0);
        return sum9;
    end
    endfunction

    // ==============================
    // Task: Apply one test vector & check
    // ==============================
    task automatic apply_and_check(
        input logic [7:0] tvA,
        input logic [7:0] tvB,
        input logic tvS1,
        input logic tvS0,
        input logic tvCin,
        input string  test_label   // "Zero", "Direct", "Random"
    );
        int unsigned expected;
        logic [7:0] expF;
        logic expC;
        string passfail;
    begin
        A = tvA;
        B = tvB;
        S1 = tvS1;
        S0 = tvS0;
        Cin = tvCin;
        #1; // small settle delay

        expected = ref_model(A, B, S1, S0, Cin);
        expF = expected[7:0];
        expC = expected[8];

        total_tests++;
        test_count++;

        if ((F !== expF) || (Cout !== expC)) begin
            passfail = "FAIL";
            errors++;
        end else begin
            passfail = "PASS";
            test_pass++;
        end

   
        $display("[TIME: %6t] [%s] A=%02h B=%02h S1S0=%b%b Cin=%b | F=%02h Cout=%b",
                 $time, test_label, A, B, S1, S0, Cin, F, Cout);
        $display("=> %4s: Expect: %02h (%0d), DUT: %02h (%0d)",
                 passfail, expF, expF, F, F);

        if (passfail == "FAIL") begin
            $display("    >>> MISMATCH: Expected F=%02h Cout=%b | Got F=%02h Cout=%b",
                     expF, expC, F, Cout);
        end
        $display("------------------------------------------------------------");
    end
    endtask

    // ==============================
    // Task: Main run_test
    // ==============================
    task automatic run_test();
        logic [7:0] edgeA [0:6];
        logic [7:0] edgeB [0:6];
        int idx;
        int s1, s0, c;
        int rctl;
    begin
        total_tests = 0;
        errors = 0;
        test_count = 0;
        test_pass = 0;

        // --- Directed edge cases ---
        edgeA[0] = 8'h00; edgeB[0] = 8'h00;
        edgeA[1] = 8'hFF; edgeB[1] = 8'hFF;
        edgeA[2] = 8'hFF; edgeB[2] = 8'h01;
        edgeA[3] = 8'h80; edgeB[3] = 8'h80;
        edgeA[4] = 8'hAA; edgeB[4] = 8'h55;
        edgeA[5] = 8'h55; edgeB[5] = 8'hAA;
        edgeA[6] = 8'h0F; edgeB[6] = 8'hF0;

        $display("\n========== STARTING DIRECTED TESTS ==========\n");
        for (idx = 0; idx <= 6; idx++) begin
            for (s1 = 0; s1 < 2; s1++) begin
                for (s0 = 0; s0 < 2; s0++) begin
                    for (c = 0; c < 2; c++) begin
                        apply_and_check(edgeA[idx], edgeB[idx], s1, s0, c, "Direct");
                    end
                end
            end
        end

        // Special case: all zero
        $display("\n========== ZERO CASE TEST ==========\n");
        apply_and_check(8'h00, 8'h00, 0, 0, 0, "Zero");

        // Randomized tests
        $display("\n========== STARTING RANDOM TESTS ==========\n");
        seed = 32'hCAFEBABE;
        while (total_tests < 100) begin
            A = $urandom(seed) & 8'hFF;
            B = $urandom(seed + 1) & 8'hFF;
            rctl = $urandom(seed + 2) % 8;
            S1 = (rctl >> 2) & 1;
            S0 = (rctl >> 1) & 1;
            Cin = rctl & 1;
            #1;
            apply_and_check(A, B, S1, S0, Cin, "Random");
            seed = seed + 12345;
        end
    end
    endtask

    // ==============================
    // Test runner & summary
    // ==============================
    initial begin
        real pass_rate;

        $display("=== TB ALU8 start ===");
        total_tests = 0;
        errors = 0;
        test_count = 0;
        test_pass = 0;

        run_test();

        // ---- SUMMARY ----
        $display("\n============================================");
        $display("=============== TEST SUMMARY ===============");
        $display("Total test cases : %0d", test_count);
        $display("Passed            : %0d", test_pass);
        $display("Failed            : %0d", test_count - test_pass);
        pass_rate = (test_count == 0) ? 0.0 : (100.0 * test_pass) / test_count;
        $display("Pass rate         : %6.2f %%", pass_rate);
        $display("============================================\n");

        if (errors == 0) begin
            $display("PASS: All tests succeeded.");
            $finish;
        end else begin
            $display("FAIL: %0d errors detected.", errors);
            $fatal;
        end
    end

endmodule

03_test/Question5/Verilator/tb_Question5.vcd
$version Generated by VerilatedVcd $end
$timescale 1ps $end
 $scope module TOP $end
  $scope module tb_Question5 $end
   $var wire 8 # A [7:0] $end
   $var wire 8 $ B [7:0] $end
   $var wire 1 % S1 $end
   $var wire 1 & S0 $end
   $var wire 1 ' Cin $end
   $var wire 8 A F [7:0] $end
   $var wire 1 B Cout $end
   $var wire 32 ( total_tests [31:0] $end
   $var wire 32 ) errors [31:0] $end
   $var wire 32 * test_count [31:0] $end
   $var wire 32 + test_pass [31:0] $end
   $var wire 32 , seed [31:0] $end
   $scope module dut $end
    $var wire 8 # A [7:0] $end
    $var wire 8 $ B [7:0] $end
    $var wire 1 % S1 $end
    $var wire 1 & S0 $end
    $var wire 1 ' Cin $end
    $var wire 8 A F [7:0] $end
    $var wire 1 B Cout $end
    $var wire 8 - B_comp [7:0] $end
    $var wire 1 0 sel_op1 $end
    $var wire 8 1 Op1 [7:0] $end
    $var wire 8 2 Op2 [7:0] $end
    $scope module u_adder $end
     $var wire 8 1 A [7:0] $end
     $var wire 8 2 B [7:0] $end
     $var wire 1 ' Cin $end
     $var wire 8 A Sum [7:0] $end
     $var wire 1 B Cout $end
     $var wire 2 3 Gblk [1:0] $end
     $var wire 2 4 Pblk [1:0] $end
     $var wire 3 C Cblk [2:0] $end
     $scope module BLK[0] $end
      $scope module u4 $end
       $var wire 4 5 A [3:0] $end
       $var wire 4 6 B [3:0] $end
       $var wire 1 D cin $end
       $var wire 1 N cout $end
       $var wire 1 7 Pblk $end
       $var wire 1 8 Gblk $end
       $var wire 4 E sum [3:0] $end
       $var wire 4 9 g [3:0] $end
       $var wire 4 : p [3:0] $end
       $var wire 1 F c1 $end
       $var wire 1 G c2 $end
       $var wire 1 H c3 $end
      $upscope $end
     $upscope $end
     $scope module BLK[1] $end
      $scope module u4 $end
       $var wire 4 ; A [3:0] $end
       $var wire 4 < B [3:0] $end
       $var wire 1 I cin $end
       $var wire 1 O cout $end
       $var wire 1 = Pblk $end
       $var wire 1 > Gblk $end
       $var wire 4 J sum [3:0] $end
       $var wire 4 ? g [3:0] $end
       $var wire 4 @ p [3:0] $end
       $var wire 1 K c1 $end
       $var wire 1 L c2 $end
       $var wire 1 M c3 $end
      $upscope $end
     $upscope $end
    $upscope $end
   $upscope $end
   $scope module unnamedblk1 $end
    $var real 64 . pass_rate $end
   $upscope $end
  $upscope $end
 $upscope $end
$enddefinitions $end


#0
b00000000 #
b00000000 $
0%
0&
0'
b00000000000000000000000000000000 (
b00000000000000000000000000000000 )
b00000000000000000000000000000000 *
b00000000000000000000000000000000 +
b00000000000000000000000000000000 ,
b11111111 -
r0 .
00
b00000000 1
b00000000 2
b00 3
b00 4
b0000 5
b0000 6
07
08
b0000 9
b0000 :
b0000 ;
b0000 <
0=
0>
b0000 ?
b0000 @
b00000000 A
0B
b000 C
0D
b0000 E
0F
0G
0H
0I
b0000 J
0K
0L
0M
0N
0O
#1000
1'
b00000000000000000000000000000001 (
b00000000000000000000000000000001 *
b00000000000000000000000000000001 +
b00000001 A
b001 C
1D
b0001 E
#2000
1&
0'
b00000000000000000000000000000010 (
b00000000000000000000000000000010 *
b00000000000000000000000000000010 +
b00000000 A
b000 C
0D
b0000 E
#3000
1'
b00000000000000000000000000000011 (
b00000000000000000000000000000011 *
b00000000000000000000000000000011 +
b00000001 A
b001 C
1D
b0001 E
#4000
1%
0&
0'
b00000000000000000000000000000100 (
b00000000000000000000000000000100 *
b00000000000000000000000000000100 +
10
b11111111 1
b11 4
b1111 5
17
b1111 :
b1111 ;
1=
b1111 @
b11111111 A
b000 C
0D
b1111 E
b1111 J
#5000
1'
b00000000000000000000000000000101 (
b00000000000000000000000000000101 *
b00000000000000000000000000000101 +
b00000000 A
1B
b111 C
1D
b0000 E
1F
1G
1H
1I
b0000 J
1K
1L
1M
1N
1O
#6000
1&
0'
b00000000000000000000000000000110 (
b00000000000000000000000000000110 *
b00000000000000000000000000000110 +
00
b00000000 1
b11111111 2
b0000 5
b1111 6
b0000 ;
b1111 <
b11111111 A
0B
b000 C
0D
b1111 E
0F
0G
0H
0I
b1111 J
0K
0L
0M
0N
0O
#7000
1'
b00000000000000000000000000000111 (
b00000000000000000000000000000111 *
b00000000000000000000000000000111 +
b00000000 A
1B
b111 C
1D
b0000 E
1F
1G
1H
1I
b0000 J
1K
1L
1M
1N
1O
#8000
b11111111 #
b11111111 $
0%
0&
0'
b00000000000000000000000000001000 (
b00000000000000000000000000001000 *
b00000000000000000000000000001000 +
b00000000 -
b11111111 1
b11 3
b00 4
b1111 5
07
18
b1111 9
b0000 :
b1111 ;
0=
1>
b1111 ?
b0000 @
b11111110 A
b110 C
0D
b1110 E
b1111 J
#9000
1'
b00000000000000000000000000001001 (
b00000000000000000000000000001001 *
b00000000000000000000000000001001 +
b11111111 A
b111 C
1D
b1111 E
#10000
1&
0'
b00000000000000000000000000001010 (
b00000000000000000000000000001010 *
b00000000000000000000000000001010 +
b00000000 2
b00 3
b11 4
b0000 6
17
08
b0000 9
b1111 :
b0000 <
1=
0>
b0000 ?
b1111 @
0B
b000 C
0D
0F
0G
0H
0I
0K
0L
0M
0N
0O
#11000
1'
b00000000000000000000000000001011 (
b00000000000000000000000000001011 *
b00000000000000000000000000001011 +
b00000000 A
1B
b111 C
1D
b0000 E
1F
1G
1H
1I
b0000 J
1K
1L
1M
1N
1O
#12000
1%
0&
0'
b00000000000000000000000000001100 (
b00000000000000000000000000001100 *
b00000000000000000000000000001100 +
10
b00000000 1
b00 4
b0000 5
07
b0000 :
b0000 ;
0=
b0000 @
0B
b000 C
0D
0F
0G
0H
0I
0K
0L
0M
0N
0O
#13000
1'
b00000000000000000000000000001101 (
b00000000000000000000000000001101 *
b00000000000000000000000000001101 +
b00000001 A
b001 C
1D
b0001 E
#14000
1&
0'
b00000000000000000000000000001110 (
b00000000000000000000000000001110 *
b00000000000000000000000000001110 +
00
b11111111 1
b11 4
b1111 5
17
b1111 :
b1111 ;
1=
b1111 @
b11111111 A
b000 C
0D
b1111 E
b1111 J
#15000
1'
b00000000000000000000000000001111 (
b00000000000000000000000000001111 *
b00000000000000000000000000001111 +
b00000000 A
1B
b111 C
1D
b0000 E
1F
1G
1H
1I
b0000 J
1K
1L
1M
1N
1O
#16000
b00000001 $
0%
0&
0'
b00000000000000000000000000010000 (
b00000000000000000000000000010000 *
b00000000000000000000000000010000 +
b11111110 -
b00000001 2
b01 3
b10 4
b0001 6
07
18
b0001 9
b1110 :
b110 C
0D
#17000
1'
b00000000000000000000000000010001 (
b00000000000000000000000000010001 *
b00000000000000000000000000010001 +
b00000001 A
b111 C
1D
b0001 E
#18000
1&
0'
b00000000000000000000000000010010 (
b00000000000000000000000000010010 *
b00000000000000000000000000010010 +
b00000000 2
b00 3
b11 4
b0000 6
17
08
b0000 9
b1111 :
b11111111 A
0B
b000 C
0D
b1111 E
0F
0G
0H
0I
b1111 J
0K
0L
0M
0N
0O
#19000
1'
b00000000000000000000000000010011 (
b00000000000000000000000000010011 *
b00000000000000000000000000010011 +
b00000000 A
1B
b111 C
1D
b0000 E
1F
1G
1H
1I
b0000 J
1K
1L
1M
1N
1O
#20000
1%
0&
0'
b00000000000000000000000000010100 (
b00000000000000000000000000010100 *
b00000000000000000000000000010100 +
10
b11111110 1
b10 4
b1110 5
07
b1110 :
b11111110 A
0B
b000 C
0D
b1110 E
0F
0G
0H
0I
b1111 J
0K
0L
0M
0N
0O
#21000
1'
b00000000000000000000000000010101 (
b00000000000000000000000000010101 *
b00000000000000000000000000010101 +
b11111111 A
b001 C
1D
b1111 E
#22000
1&
0'
b00000000000000000000000000010110 (
b00000000000000000000000000010110 *
b00000000000000000000000000010110 +
00
b11111111 1
b11111110 2
b11 3
b00 4
b1111 5
b1110 6
18
b1110 9
b0001 :
b1111 <
0=
1>
b1111 ?
b0000 @
b11111101 A
1B
b110 C
0D
b1101 E
1G
1H
1I
1K
1L
1M
1N
1O
#23000
1'
b00000000000000000000000000010111 (
b00000000000000000000000000010111 *
b00000000000000000000000000010111 +
b11111110 A
b111 C
1D
b1110 E
1F
#24000
b10000000 #
b10000000 $
0%
0&
0'
b00000000000000000000000000011000 (
b00000000000000000000000000011000 *
b00000000000000000000000000011000 +
b01111111 -
b10000000 1
b10000000 2
b10 3
b0000 5
b0000 6
08
b0000 9
b0000 :
b1000 ;
b1000 <
b1000 ?
b00000000 A
b100 C
0D
b0000 E
0F
0G
0H
0I
b0000 J
0K
0L
0M
0N
#25000
1'
b00000000000000000000000000011001 (
b00000000000000000000000000011001 *
b00000000000000000000000000011001 +
b00000001 A
b101 C
1D
b0001 E
#26000
1&
0'
b00000000000000000000000000011010 (
b00000000000000000000000000011010 *
b00000000000000000000000000011010 +
b00000000 2
b00 3
b0000 <
0>
b0000 ?
b1000 @
b10000000 A
0B
b000 C
0D
b0000 E
b1000 J
0O
#27000
1'
b00000000000000000000000000011011 (
b00000000000000000000000000011011 *
b00000000000000000000000000011011 +
b10000001 A
b001 C
1D
b0001 E
#28000
1%
0&
0'
b00000000000000000000000000011100 (
b00000000000000000000000000011100 *
b00000000000000000000000000011100 +
10
b01111111 1
b01 4
b1111 5
17
b1111 :
b0111 ;
b0111 @
b01111111 A
b000 C
0D
b1111 E
b0111 J
#29000
1'
b00000000000000000000000000011101 (
b00000000000000000000000000011101 *
b00000000000000000000000000011101 +
b10000000 A
b011 C
1D
b0000 E
1F
1G
1H
1I
b1000 J
1K
1L
1M
1N
#30000
1&
0'
b00000000000000000000000000011110 (
b00000000000000000000000000011110 *
b00000000000000000000000000011110 +
00
b10000000 1
b01111111 2
b11 4
b0000 5
b1111 6
b1000 ;
b0111 <
1=
b1111 @
b11111111 A
b000 C
0D
b1111 E
0F
0G
0H
0I
b1111 J
0K
0L
0M
0N
#31000
1'
b00000000000000000000000000011111 (
b00000000000000000000000000011111 *
b00000000000000000000000000011111 +
b00000000 A
1B
b111 C
1D
b0000 E
1F
1G
1H
1I
b0000 J
1K
1L
1M
1N
1O
#32000
b10101010 #
b01010101 $
0%
0&
0'
b00000000000000000000000000100000 (
b00000000000000000000000000100000 *
b00000000000000000000000000100000 +
b10101010 -
b10101010 1
b01010101 2
b1010 5
b0101 6
b1010 ;
b0101 <
b11111111 A
0B
b000 C
0D
b1111 E
0F
0G
0H
0I
b1111 J
0K
0L
0M
0N
0O
#33000
1'
b00000000000000000000000000100001 (
b00000000000000000000000000100001 *
b00000000000000000000000000100001 +
b00000000 A
1B
b111 C
1D
b0000 E
1F
1G
1H
1I
b0000 J
1K
1L
1M
1N
1O
#34000
1&
0'
b00000000000000000000000000100010 (
b00000000000000000000000000100010 *
b00000000000000000000000000100010 +
b00000000 2
b00 4
b0000 6
07
b1010 :
b0000 <
0=
b1010 @
b10101010 A
0B
b000 C
0D
b1010 E
0F
0G
0H
0I
b1010 J
0K
0L
0M
0N
0O
#35000
1'
b00000000000000000000000000100011 (
b00000000000000000000000000100011 *
b00000000000000000000000000100011 +
b10101011 A
b001 C
1D
b1011 E
#36000
1%
0&
0'
b00000000000000000000000000100100 (
b00000000000000000000000000100100 *
b00000000000000000000000000100100 +
10
b10101010 A
b000 C
0D
b1010 E
#37000
1'
b00000000000000000000000000100101 (
b00000000000000000000000000100101 *
b00000000000000000000000000100101 +
b10101011 A
b001 C
1D
b1011 E
#38000
1&
0'
b00000000000000000000000000100110 (
b00000000000000000000000000100110 *
b00000000000000000000000000100110 +
00
b10101010 2
b11 3
b1010 6
18
b1010 9
b0000 :
b1010 <
1>
b1010 ?
b0000 @
b01010100 A
1B
b110 C
0D
b0100 E
1G
1I
b0101 J
1L
1N
1O
#39000
1'
b00000000000000000000000000100111 (
b00000000000000000000000000100111 *
b00000000000000000000000000100111 +
b01010101 A
b111 C
1D
b0101 E
#40000
b01010101 #
b10101010 $
0%
0&
0'
b00000000000000000000000000101000 (
b00000000000000000000000000101000 *
b00000000000000000000000000101000 +
b01010101 -
b01010101 1
b00 3
b11 4
b0101 5
17
08
b0000 9
b1111 :
b0101 ;
1=
0>
b0000 ?
b1111 @
b11111111 A
0B
b000 C
0D
b1111 E
0G
0I
b1111 J
0L
0N
0O
#41000
1'
b00000000000000000000000000101001 (
b00000000000000000000000000101001 *
b00000000000000000000000000101001 +
b00000000 A
1B
b111 C
1D
b0000 E
1F
1G
1H
1I
b0000 J
1K
1L
1M
1N
1O
#42000
1&
0'
b00000000000000000000000000101010 (
b00000000000000000000000000101010 *
b00000000000000000000000000101010 +
b00000000 2
b00 4
b0000 6
07
b0101 :
b0000 <
0=
b0101 @
b01010101 A
0B
b000 C
0D
b0101 E
0F
0G
0H
0I
b0101 J
0K
0L
0M
0N
0O
#43000
1'
b00000000000000000000000000101011 (
b00000000000000000000000000101011 *
b00000000000000000000000000101011 +
b01010110 A
b001 C
1D
b0110 E
1F
#44000
1%
0&
0'
b00000000000000000000000000101100 (
b00000000000000000000000000101100 *
b00000000000000000000000000101100 +
10
b01010101 A
b000 C
0D
b0101 E
0F
#45000
1'
b00000000000000000000000000101101 (
b00000000000000000000000000101101 *
b00000000000000000000000000101101 +
b01010110 A
b001 C
1D
b0110 E
1F
#46000
1&
0'
b00000000000000000000000000101110 (
b00000000000000000000000000101110 *
b00000000000000000000000000101110 +
00
b01010101 2
b0101 6
b0101 9
b0000 :
b0101 <
b0101 ?
b0000 @
b10101010 A
b000 C
0D
b1010 E
1H
b1010 J
1K
1M
#47000
1'
b00000000000000000000000000101111 (
b00000000000000000000000000101111 *
b00000000000000000000000000101111 +
b10101011 A
b001 C
1D
b1011 E
#48000
b00001111 #
b11110000 $
0%
0&
0'
b00000000000000000000000000110000 (
b00000000000000000000000000110000 *
b00000000000000000000000000110000 +
b00001111 -
b00001111 1
b11110000 2
b11 4
b1111 5
b0000 6
17
b0000 9
b1111 :
b0000 ;
b1111 <
1=
b0000 ?
b1111 @
b11111111 A
b000 C
0D
b1111 E
0F
0H
b1111 J
0K
0M
#49000
1'
b00000000000000000000000000110001 (
b00000000000000000000000000110001 *
b00000000000000000000000000110001 +
b00000000 A
1B
b111 C
1D
b0000 E
1F
1G
1H
1I
b0000 J
1K
1L
1M
1N
1O
#50000
1&
0'
b00000000000000000000000000110010 (
b00000000000000000000000000110010 *
b00000000000000000000000000110010 +
b00000000 2
b01 4
b0000 <
0=
b0000 @
b00001111 A
0B
b000 C
0D
b1111 E
0F
0G
0H
0I
0K
0L
0M
0N
0O
#51000
1'
b00000000000000000000000000110011 (
b00000000000000000000000000110011 *
b00000000000000000000000000110011 +
b00010000 A
b011 C
1D
b0000 E
1F
1G
1H
1I
b0001 J
1N
#52000
1%
0&
0'
b00000000000000000000000000110100 (
b00000000000000000000000000110100 *
b00000000000000000000000000110100 +
10
b00001111 A
b000 C
0D
b1111 E
0F
0G
0H
0I
b0000 J
0N
#53000
1'
b00000000000000000000000000110101 (
b00000000000000000000000000110101 *
b00000000000000000000000000110101 +
b00010000 A
b011 C
1D
b0000 E
1F
1G
1H
1I
b0001 J
1N
#54000
1&
0'
b00000000000000000000000000110110 (
b00000000000000000000000000110110 *
b00000000000000000000000000110110 +
00
b00001111 2
b01 3
b00 4
b1111 6
07
18
b1111 9
b0000 :
b00011110 A
b010 C
0D
b1110 E
#55000
1'
b00000000000000000000000000110111 (
b00000000000000000000000000110111 *
b00000000000000000000000000110111 +
b00011111 A
b011 C
1D
b1111 E
#56000
b00000000 #
b00000000 $
0%
0&
0'
b00000000000000000000000000111000 (
b00000000000000000000000000111000 *
b00000000000000000000000000111000 +
b11111111 -
b00000000 1
b00000000 2
b00 3
b0000 5
b0000 6
08
b0000 9
b00000000 A
b000 C
0D
b0000 E
0F
0G
0H
0I
b0000 J
0N
#57000
b01111100 #
b01111110 $
b00000000000000000000000000111001 (
b00000000000000000000000000111001 *
b00000000000000000000000000111001 +
b11001010111111101011101010111110 ,
b10000001 -
b01111100 1
b01111110 2
b01 3
b1100 5
b1110 6
18
b1100 9
b0010 :
b0111 ;
b0111 <
b0111 ?
b11111010 A
b010 C
b1010 E
1H
1I
b1111 J
1K
1L
1M
1N
#58000
#59000
b11101110 #
b11110000 $
1&
b00000000000000000000000000111010 (
b00000000000000000000000000111010 *
b00000000000000000000000000111010 +
b11001010111111101110101011110111 ,
b00001111 -
b11101110 1
b00000000 2
b00 3
b1110 5
b0000 6
08
b0000 9
b1110 :
b1110 ;
b0000 <
b0000 ?
b1110 @
b11101110 A
b000 C
b1110 E
0H
0I
b1110 J
0K
0L
0M
0N
#60000
#61000
b01100000 #
b01100010 $
1%
0&
b00000000000000000000000000111011 (
b00000000000000000000000000111011 *
b00000000000000000000000000111011 +
b11001010111111110001101100110000 ,
b10011101 -
10
b10011101 1
b1101 5
b1101 :
b1001 ;
b1001 @
b10011101 A
b1101 E
b1001 J
#62000
#63000
b11010010 #
b11010100 $
1&
b00000000000000000000000000111100 (
b00000000000000000000000000111100 *
b00000000000000000000000000111100 +
b11001010111111110100101101101001 ,
b00101011 -
00
b11010010 1
b00101011 2
b10 4
b0010 5
b1011 6
b0010 9
b1001 :
b1101 ;
b0010 <
1=
b1111 @
b11111101 A
1G
b1111 J
#64000
#65000
b01000100 #
b01000110 $
0%
0&
b00000000000000000000000000111101 (
b00000000000000000000000000111101 *
b00000000000000000000000000111101 +
b11001010111111110111101110100010 ,
b10111001 -
b01000100 1
b01000110 2
b00 4
b0100 5
b0110 6
b0100 9
b0010 :
b0100 ;
b0100 <
0=
b0100 ?
b0000 @
b10001010 A
b1010 E
0G
1H
b1000 J
1M
#66000
#67000
b10110110 #
b10111000 $
1&
b00000000000000000000000000111110 (
b00000000000000000000000000111110 *
b00000000000000000000000000111110 +
b11001010111111111010101111011011 ,
b01000111 -
b10110110 1
b00000000 2
b0110 5
b0000 6
b0000 9
b0110 :
b1011 ;
b0000 <
b0000 ?
b1011 @
b10110110 A
b0110 E
0H
b1011 J
0M
#68000
#69000
b00101000 #
b00101010 $
1%
0&
b00000000000000000000000000111111 (
b00000000000000000000000000111111 *
b00000000000000000000000000111111 +
b11001010111111111101110000010100 ,
b11010101 -
10
b11010101 1
b0101 5
b0101 :
b1101 ;
b1101 @
b11010101 A
b0101 E
b1101 J
#70000
#71000
b10011010 #
b10011100 $
1&
b00000000000000000000000001000000 (
b00000000000000000000000001000000 *
b00000000000000000000000001000000 +
b11001011000000000000110001001101 ,
b01100011 -
00
b10011010 1
b01100011 2
b10 4
b1010 5
b0011 6
b0010 9
b1001 :
b1001 ;
b0110 <
1=
b1111 @
b11111101 A
b1101 E
1G
b1111 J
#72000
#73000
b00001100 #
b00001110 $
0%
0&
b00000000000000000000000001000001 (
b00000000000000000000000001000001 *
b00000000000000000000000001000001 +
b11001011000000000011110010000110 ,
b11110001 -
b00001100 1
b00001110 2
b01 3
b00 4
b1100 5
b1110 6
18
b1100 9
b0010 :
b0000 ;
b0000 <
0=
b0000 @
b00011010 A
b010 C
b1010 E
0G
1H
1I
b0001 J
1N
#74000
#75000
b01111110 #
b10000000 $
1&
b00000000000000000000000001000010 (
b00000000000000000000000001000010 *
b00000000000000000000000001000010 +
b11001011000000000110110010111111 ,
b01111111 -
b01111110 1
b00000000 2
b00 3
b1110 5
b0000 6
08
b0000 9
b1110 :
b0111 ;
b0111 @
b01111110 A
b000 C
b1110 E
0H
0I
b0111 J
0N
#76000
#77000
b11110000 #
b11110010 $
1%
0&
b00000000000000000000000001000011 (
b00000000000000000000000001000011 *
b00000000000000000000000001000011 +
b11001011000000001001110011111000 ,
b00001101 -
10
b00001101 1
b1101 5
b1101 :
b0000 ;
b0000 @
b00001101 A
b1101 E
b0000 J
#78000
#79000
b01100010 #
b01100100 $
1&
b00000000000000000000000001000100 (
b00000000000000000000000001000100 *
b00000000000000000000000001000100 +
b11001011000000001100110100110001 ,
b10011011 -
00
b01100010 1
b10011011 2
b10 4
b0010 5
b1011 6
b0010 9
b1001 :
b0110 ;
b1001 <
1=
b1111 @
b11111101 A
1G
b1111 J
#80000
#81000
b11010100 #
b11010110 $
0%
0&
b00000000000000000000000001000101 (
b00000000000000000000000001000101 *
b00000000000000000000000001000101 +
b11001011000000001111110101101010 ,
b00101001 -
b11010100 1
b11010110 2
b10 3
b00 4
b0100 5
b0110 6
b0100 9
b0010 :
b1101 ;
b1101 <
0=
1>
b1101 ?
b0000 @
b10101010 A
1B
b100 C
b1010 E
0G
1H
b1010 J
1K
1M
1O
#82000
#83000
b01000110 #
b01001000 $
1&
b00000000000000000000000001000110 (
b00000000000000000000000001000110 *
b00000000000000000000000001000110 +
b11001011000000010010110110100011 ,
b10110111 -
b01000110 1
b00000000 2
b00 3
b0110 5
b0000 6
b0000 9
b0110 :
b0100 ;
b0000 <
0>
b0000 ?
b0100 @
b01000110 A
0B
b000 C
b0110 E
0H
b0100 J
0K
0M
0O
#84000
#85000
b10111000 #
b10111010 $
1%
0&
b00000000000000000000000001000111 (
b00000000000000000000000001000111 *
b00000000000000000000000001000111 +
b11001011000000010101110111011100 ,
b01000101 -
10
b01000101 1
b0101 5
b0101 :
b01000101 A
b0101 E
#86000
#87000
b00101010 #
b00101100 $
1&
b00000000000000000000000001001000 (
b00000000000000000000000001001000 *
b00000000000000000000000001001000 +
b11001011000000011000111000010101 ,
b11010011 -
00
b00101010 1
b11010011 2
b10 4
b1010 5
b0011 6
b0010 9
b1001 :
b0010 ;
b1101 <
1=
b1111 @
b11111101 A
b1101 E
1G
b1111 J
#88000
