02_rtl/Question2/LOPD_4bit.sv
module LOPD_4bit(
    input logic [3:0]       i_data  ,
    output logic [1:0]      o_pos_one,
    output logic            o_zero_flag
);

/////////////////// LDO ///////////////////
// D[3] | D[2] | D[1] | D[0] |PO[3] | PO[2] | PO[1] | PO[0] | ZERO_FLAG |
//   0  |   0  |   0  |   0  |  0   |   0   |   0   |   0   |     1     |
//   0  |   0  |   0  |   1  |  0   |   0   |   0   |   1   |     0     |
//   0  |   0  |   1  |   X  |  0   |   0   |   1   |   0   |     0     |
//   0  |   1  |   X  |   X  |  0   |   1   |   0   |   0   |     0     |
//   1  |   X  |   X  |   X  |  1   |   0   |   0   |   0   |     0     |
/////////////////// LDOD ///////////////////
// D[3] | D[2] | D[1] | D[0] | PO[1] | PO[0] | ZERO_FLAG |
//   0  |   0  |   0  |   0  |   0   |   0   |     1     |
//   0  |   0  |   0  |   1  |   0   |   0   |     0     |
//   0  |   0  |   1  |   X  |   0   |   1   |     0     |
//   0  |   1  |   X  |   X  |   1   |   0   |     0     |
//   1  |   X  |   X  |   X  |   1   |   1   |     0     |

assign o_zero_flag = ~((o_pos_one[1])|(i_data[1]|i_data[0])) ;
assign o_pos_one[1] = i_data[3] | i_data[2];
assign o_pos_one[0] = ((~o_pos_one[1]) & (i_data[1])) |  (i_data[3]);

endmodule

02_rtl/Question2/LOPD_8bit.sv
module LOPD_8bit(
    input logic [7:0]       i_data  ,
    output logic [2:0]      o_pos_one,
    output logic            o_zero_flag
);

////////////////////////////////////////////////////////////
// LOPD_4bit_unit_0
////////////////////////////////////////////////////////////
logic w_zero_flag_0;
logic [1:0] w_pos_one_0;
LOPD_4bit LOPD_4bit_unit_0 (
    .i_data         (i_data[3:0]),
    .o_pos_one      (w_pos_one_0),
    .o_zero_flag    (w_zero_flag_0)
);

////////////////////////////////////////////////////////////
// LOPD_4bit_unit_1
////////////////////////////////////////////////////////////
logic w_zero_flag_1;
logic [1:0] w_pos_one_1;
LOPD_4bit LOPD_4bit_unit_1 (
    .i_data         (i_data[7:4]),
    .o_pos_one      (w_pos_one_1),
    .o_zero_flag    (w_zero_flag_1)
);

////////////////////////////////////////////////////////////
// LOD_8bit_unit
////////////////////////////////////////////////////////////
assign o_zero_flag = w_zero_flag_0 & w_zero_flag_1;
assign o_pos_one[2] = ~(w_zero_flag_1);
assign o_pos_one[1] = (w_zero_flag_1) ? w_pos_one_0[1] : w_pos_one_1[1];
assign o_pos_one[0] = (w_zero_flag_1) ? w_pos_one_0[0] : w_pos_one_1[0];

endmodule

02_rtl/Question2/LOPD_16bit.sv
module LOPD_16bit(
    input logic [15:0]       i_data  ,
    output logic [3:0]      o_pos_one,
    output logic            o_zero_flag
);


////////////////////////////////////////////////////////////
// LOPD_8bit_unit_0
////////////////////////////////////////////////////////////
logic [2:0]         w_pos_one_0;  
logic               w_zero_flag_0;
LOPD_8bit LOPD_8bit_unit_0(
    .i_data         (i_data[7:0]),
    .o_pos_one      (w_pos_one_0),
    .o_zero_flag    (w_zero_flag_0)
);
////////////////////////////////////////////////////////////
// LOPD_8bit_unit_1
////////////////////////////////////////////////////////////
logic [2:0]         w_pos_one_1;  
logic               w_zero_flag_1;
LOPD_8bit LOPD_8bit_unit_1(
    .i_data         (i_data[15:8]),
    .o_pos_one      (w_pos_one_1),
    .o_zero_flag    (w_zero_flag_1)
);

////////////////////////////////////////////////////////////
// LOD_16bit_unit
////////////////////////////////////////////////////////////
assign o_zero_flag = w_zero_flag_0 & w_zero_flag_1;
assign o_pos_one[3] = ~(w_zero_flag_1);
assign o_pos_one[2] = w_zero_flag_1 ? w_pos_one_0[2] : w_pos_one_1[2];
assign o_pos_one[1] = w_zero_flag_1 ? w_pos_one_0[1] : w_pos_one_1[1];
assign o_pos_one[0] = w_zero_flag_1 ? w_pos_one_0[0] : w_pos_one_1[0];
endmodule

03_verif/Question2/coverage/annotated_src/Question2.sv
//      // verilator_coverage annotation
        module Question2 #(
            parameter SIZE_DATA     = 24    ,
            parameter SIZE_LOPD     = 5      
        )(
 000376     input logic [SIZE_DATA-1:0]     i_data          ,
 000282     output logic [SIZE_LOPD-1:0]    o_one_position  ,
%000002     output logic                    o_zero_flag      
        );
        
 000376 logic [15:0]     LOPD16_i_data;
        assign LOPD16_i_data = i_data[15:0];
 000440 logic [3:0]      LOPD16_o_pos_one;
 000297 logic            LOPD16_o_zero_flag;
 000385 logic [7:0]      LOPD8_i_data;
        assign LOPD8_i_data = i_data[23:16];
 000474 logic [2:0]      LOPD8_o_pos_one;
 000434 logic            LOPD8_o_zero_flag;
        LOPD_16bit LOPD_16bit_UNIT_LSB (
            .i_data             (LOPD16_i_data),
            .o_pos_one          (LOPD16_o_pos_one),
            .o_zero_flag        (LOPD16_o_zero_flag)
        );
        
        LOPD_8bit LOPD_8bit_UNIT_MSB (
            .i_data             (LOPD8_i_data),
            .o_pos_one          (LOPD8_o_pos_one),
            .o_zero_flag        (LOPD8_o_zero_flag)
        );
        
        assign o_zero_flag = LOPD16_o_zero_flag & LOPD8_o_zero_flag;
        assign o_one_position[4] = ~LOPD8_o_zero_flag;
        assign o_one_position[3] = LOPD8_o_zero_flag ? LOPD16_o_pos_one[3] : 1'b0;
        assign o_one_position[2] = LOPD8_o_zero_flag ? LOPD16_o_pos_one[2] : LOPD8_o_pos_one[2];
        assign o_one_position[1] = LOPD8_o_zero_flag ? LOPD16_o_pos_one[1] : LOPD8_o_pos_one[1];
        assign o_one_position[0] = LOPD8_o_zero_flag ? LOPD16_o_pos_one[0] : LOPD8_o_pos_one[0];
        
        endmodule

03_verif/Question2/coverage/annotated_src/Question2_unit.sv
//      // verilator_coverage annotation
        module Question2_unit #(
            parameter SIZE_DATA     = 24 ,
            parameter SIZE_LOP      = 5
        )(
 002073     input logic                     i_clk   ,
%000001     input logic                     i_rst_n ,
%000002     input logic [SIZE_DATA-1:0]     i_addr  ,
 000376     input logic [SIZE_DATA-1:0]     i_data  ,
%000002     output logic [SIZE_DATA-1:0]    o_addr  ,
 000282     output logic [SIZE_LOP-1:0]     o_one_position,
%000002     output logic                    o_zero_flag    
        );
        
        // logic [SIZE_DATA-1:0] w_i_addr, w_i_data;
%000000 logic [SIZE_DATA-1:0] w_o_addr;
 000282 logic [SIZE_LOP-1:0] w_one_position;
%000002 logic w_zero_flag;
 001037 always_ff @( posedge i_clk or negedge i_rst_n ) begin : flipflop_proc
%000002     if(~i_rst_n) begin
                // w_i_addr        <= '0;
                // w_i_data        <= '0;
%000002         o_addr          <= '0;
%000002         o_one_position  <= '0;
%000002         o_zero_flag     <= '0;
 001035     end else begin
                // w_i_addr        <= i_addr;
                // w_i_data        <= i_data;
 001035         o_addr          <= i_addr;
 001035         o_one_position  <= w_one_position;
 001035         o_zero_flag     <= w_zero_flag;
            end
        end
        
        // assign w_o_addr = w_i_addr;
        
        Question2 #(
            .SIZE_DATA      (24    ),
            .SIZE_LOPD      (5     ) 
        ) DUT (
            .i_data         (i_data),
            .o_one_position (w_one_position),
            .o_zero_flag    (w_zero_flag) 
        );
        
        endmodule

03_verif/Question2/tb_Question2.sv
`timescale 1ns/1ps

module tb_Question2();

parameter SIZE_DATA = 24;
parameter SIZE_LOP  = 5;

logic i_clk, i_rst_n;
logic [SIZE_DATA-1:0] i_addr;
logic [SIZE_DATA-1:0] i_data;
logic [SIZE_DATA-1:0] o_addr;  
logic [SIZE_LOP-1:0]  o_one_position;
logic                 o_zero_flag;

//===================== DUT =====================//
Question2_unit #(
    .SIZE_DATA (SIZE_DATA),
    .SIZE_LOP  (SIZE_LOP)
) DUT (
    .i_clk          (i_clk),
    .i_rst_n        (i_rst_n),
    .i_addr         (i_addr),
    .i_data         (i_data),
    .o_addr         (o_addr),
    .o_one_position (o_one_position),
    .o_zero_flag    (o_zero_flag)
);

//===================== CLOCK =====================//
initial begin
    i_clk = 0;
    forever #5 i_clk = ~i_clk; // 10ns period = 100MHz
end

//===================== DUMP WAVE =====================//
initial begin
    $dumpfile("tb_Question2.vcd");
    $dumpvars(0, tb_Question2);
end
int bit_pos;
//===================== TEST SEQUENCE =====================//
initial begin
    i_rst_n = 0;
    i_addr  = '0;
    i_data  = '0;

    // Reset phase
    #20;
    i_rst_n = 1;
    #10;

    // Random test 100 lần
    bit_pos = 1;
    repeat (24) begin
        #1;
        i_addr = i_addr + 1;
        i_data  = bit_pos;   
        @(posedge i_clk);
        bit_pos = bit_pos << 1'b1;
    end
    repeat (1000) begin
        #1;
        
        // Chọn vị trí bit 1 ngẫu nhiên từ 0 → 23
        bit_pos = $urandom_range(0, SIZE_DATA-1);
        
        // Tạo dữ liệu chỉ có một bit 1 tại vị trí đó
        i_data = 24'b1 << bit_pos;
        
        // Có thể thêm vài bit 1 ngẫu nhiên khác (tùy muốn)
        if ($urandom_range(0, 1)) begin
            i_data |= $urandom_range(0, (1 << SIZE_DATA) - 1);
        end
        
        // Random địa chỉ cho vui
        i_addr = i_addr + 1;
        @(posedge i_clk);
end


    #100;
    $finish;
end

//===================== MONITOR / DISPLAY =====================//
always @(*) begin
    @(posedge i_clk); // Clock input addr
    $display("[%0t] i_addr = %h | i_data = %b (%0d)", $time, i_addr, i_data, i_data);
    $display("o_addr = %h \t| o_one_position = %b (%0d) \t| o_zero_flag = %b", o_addr, o_one_position, o_one_position, o_zero_flag);    
    // @(posedge i_clk); // Clock processing data
end

endmodule

03_verif/Question2/coverage/annotated_src/LOPD_32bit.sv
//      // verilator_coverage annotation
        module LOPD_32bit (
%000000     input logic [31:0]          i_data      ,
%000000     output logic [4:0]          o_pos_one   ,
%000001     output logic                o_zero_flag  
        );
        
        ////////////////////////////////////////////////////////////
        // LOPD_16bit_unit_0
        ////////////////////////////////////////////////////////////
%000000 logic [3:0]         w_pos_one_0;  
%000001 logic               w_zero_flag_0;
        LOPD_16bit LOPD_16bit_unit_0(
            .i_data         (i_data[15:0]),
            .o_pos_one      (w_pos_one_0),
            .o_zero_flag    (w_zero_flag_0)
        );
        ////////////////////////////////////////////////////////////
        // LOPD_16bit_unit_1
        ////////////////////////////////////////////////////////////
%000000 logic [3:0]         w_pos_one_1;  
%000001 logic               w_zero_flag_1;
        LOPD_16bit LOPD_16bit_unit_1(
            .i_data         (i_data[31:16]),
            .o_pos_one      (w_pos_one_1),
            .o_zero_flag    (w_zero_flag_1)
        );
        
        ////////////////////////////////////////////////////////////
        // LOD_16bit_unit
        ////////////////////////////////////////////////////////////
        assign o_zero_flag = w_zero_flag_0 & w_zero_flag_1;
        assign o_pos_one[4] = ~(w_zero_flag_1);
        assign o_pos_one[3] = w_zero_flag_1 ? w_pos_one_0[3] : w_pos_one_1[3];
        assign o_pos_one[2] = w_zero_flag_1 ? w_pos_one_0[2] : w_pos_one_1[2];
        assign o_pos_one[1] = w_zero_flag_1 ? w_pos_one_0[1] : w_pos_one_1[1];
        assign o_pos_one[0] = w_zero_flag_1 ? w_pos_one_0[0] : w_pos_one_1[0];
        
        endmodule

03_verif/Question2/tb_Question2.vcd
$version Generated by VerilatedVcd $end
$timescale 1ps $end
 $scope module TOP $end
  $var wire 32 4 i_data [31:0] $end
  $var wire 5 5 o_pos_one [4:0] $end
  $var wire 1 6 o_zero_flag $end
  $scope module LOPD_32bit $end
   $var wire 32 4 i_data [31:0] $end
   $var wire 5 5 o_pos_one [4:0] $end
   $var wire 1 6 o_zero_flag $end
   $var wire 4 7 w_pos_one_0 [3:0] $end
   $var wire 1 8 w_zero_flag_0 $end
   $scope module LOPD_16bit_unit_0 $end
    $var wire 16 R i_data [15:0] $end
    $var wire 4 7 o_pos_one [3:0] $end
    $var wire 1 8 o_zero_flag $end
    $var wire 3 S w_pos_one_0 [2:0] $end
    $var wire 1 T w_zero_flag_0 $end
    $var wire 3 U w_pos_one_1 [2:0] $end
    $var wire 1 V w_zero_flag_1 $end
    $scope module LOPD_8bit_unit_0 $end
     $var wire 8 W i_data [7:0] $end
     $var wire 3 S o_pos_one [2:0] $end
     $var wire 1 T o_zero_flag $end
     $var wire 1 X w_zero_flag_0 $end
     $var wire 2 Y w_pos_one_0 [1:0] $end
     $var wire 1 Z w_zero_flag_1 $end
     $var wire 2 [ w_pos_one_1 [1:0] $end
     $scope module LOPD_4bit_unit_0 $end
      $var wire 4 \ i_data [3:0] $end
      $var wire 2 Y o_pos_one [1:0] $end
      $var wire 1 X o_zero_flag $end
     $upscope $end
     $scope module LOPD_4bit_unit_1 $end
      $var wire 4 ] i_data [3:0] $end
      $var wire 2 [ o_pos_one [1:0] $end
      $var wire 1 Z o_zero_flag $end
     $upscope $end
    $upscope $end
    $scope module LOPD_8bit_unit_1 $end
     $var wire 8 ^ i_data [7:0] $end
     $var wire 3 U o_pos_one [2:0] $end
     $var wire 1 V o_zero_flag $end
     $var wire 1 _ w_zero_flag_0 $end
     $var wire 2 ` w_pos_one_0 [1:0] $end
     $var wire 1 a w_zero_flag_1 $end
     $var wire 2 b w_pos_one_1 [1:0] $end
     $scope module LOPD_4bit_unit_0 $end
      $var wire 4 c i_data [3:0] $end
      $var wire 2 ` o_pos_one [1:0] $end
      $var wire 1 _ o_zero_flag $end
     $upscope $end
     $scope module LOPD_4bit_unit_1 $end
      $var wire 4 d i_data [3:0] $end
      $var wire 2 b o_pos_one [1:0] $end
      $var wire 1 a o_zero_flag $end
     $upscope $end
    $upscope $end
   $upscope $end
   $var wire 4 9 w_pos_one_1 [3:0] $end
   $var wire 1 : w_zero_flag_1 $end
   $scope module LOPD_16bit_unit_1 $end
    $var wire 16 e i_data [15:0] $end
    $var wire 4 9 o_pos_one [3:0] $end
    $var wire 1 : o_zero_flag $end
    $var wire 3 f w_pos_one_0 [2:0] $end
    $var wire 1 g w_zero_flag_0 $end
    $var wire 3 h w_pos_one_1 [2:0] $end
    $var wire 1 i w_zero_flag_1 $end
    $scope module LOPD_8bit_unit_0 $end
     $var wire 8 j i_data [7:0] $end
     $var wire 3 f o_pos_one [2:0] $end
     $var wire 1 g o_zero_flag $end
     $var wire 1 k w_zero_flag_0 $end
     $var wire 2 l w_pos_one_0 [1:0] $end
     $var wire 1 m w_zero_flag_1 $end
     $var wire 2 n w_pos_one_1 [1:0] $end
     $scope module LOPD_4bit_unit_0 $end
      $var wire 4 o i_data [3:0] $end
      $var wire 2 l o_pos_one [1:0] $end
      $var wire 1 k o_zero_flag $end
     $upscope $end
     $scope module LOPD_4bit_unit_1 $end
      $var wire 4 p i_data [3:0] $end
      $var wire 2 n o_pos_one [1:0] $end
      $var wire 1 m o_zero_flag $end
     $upscope $end
    $upscope $end
    $scope module LOPD_8bit_unit_1 $end
     $var wire 8 q i_data [7:0] $end
     $var wire 3 h o_pos_one [2:0] $end
     $var wire 1 i o_zero_flag $end
     $var wire 1 r w_zero_flag_0 $end
     $var wire 2 s w_pos_one_0 [1:0] $end
     $var wire 1 t w_zero_flag_1 $end
     $var wire 2 u w_pos_one_1 [1:0] $end
     $scope module LOPD_4bit_unit_0 $end
      $var wire 4 v i_data [3:0] $end
      $var wire 2 s o_pos_one [1:0] $end
      $var wire 1 r o_zero_flag $end
     $upscope $end
     $scope module LOPD_4bit_unit_1 $end
      $var wire 4 w i_data [3:0] $end
      $var wire 2 u o_pos_one [1:0] $end
      $var wire 1 t o_zero_flag $end
     $upscope $end
    $upscope $end
   $upscope $end
  $upscope $end
  $scope module tb_Question2 $end
   $var wire 32 x SIZE_DATA [31:0] $end
   $var wire 32 y SIZE_LOP [31:0] $end
   $var wire 1 ; i_clk $end
   $var wire 1 # i_rst_n $end
   $var wire 24 $ i_addr [23:0] $end
   $var wire 24 % i_data [23:0] $end
   $var wire 24 1 o_addr [23:0] $end
   $var wire 5 2 o_one_position [4:0] $end
   $var wire 1 3 o_zero_flag $end
   $var wire 32 & bit_pos [31:0] $end
   $scope module DUT $end
    $var wire 32 x SIZE_DATA [31:0] $end
    $var wire 32 y SIZE_LOP [31:0] $end
    $var wire 1 ; i_clk $end
    $var wire 1 # i_rst_n $end
    $var wire 24 $ i_addr [23:0] $end
    $var wire 24 % i_data [23:0] $end
    $var wire 24 1 o_addr [23:0] $end
    $var wire 5 2 o_one_position [4:0] $end
    $var wire 1 3 o_zero_flag $end
    $var wire 24 z w_o_addr [23:0] $end
    $var wire 5 < w_one_position [4:0] $end
    $var wire 1 = w_zero_flag $end
    $scope module DUT $end
     $var wire 32 x SIZE_DATA [31:0] $end
     $var wire 32 y SIZE_LOPD [31:0] $end
     $var wire 24 % i_data [23:0] $end
     $var wire 5 < o_one_position [4:0] $end
     $var wire 1 = o_zero_flag $end
     $var wire 16 ' LOPD16_i_data [15:0] $end
     $var wire 4 > LOPD16_o_pos_one [3:0] $end
     $var wire 1 ? LOPD16_o_zero_flag $end
     $var wire 8 ( LOPD8_i_data [7:0] $end
     $var wire 3 @ LOPD8_o_pos_one [2:0] $end
     $var wire 1 A LOPD8_o_zero_flag $end
     $scope module LOPD_16bit_UNIT_LSB $end
      $var wire 16 ' i_data [15:0] $end
      $var wire 4 > o_pos_one [3:0] $end
      $var wire 1 ? o_zero_flag $end
      $var wire 3 F w_pos_one_0 [2:0] $end
      $var wire 1 G w_zero_flag_0 $end
      $var wire 3 H w_pos_one_1 [2:0] $end
      $var wire 1 I w_zero_flag_1 $end
      $scope module LOPD_8bit_unit_0 $end
       $var wire 8 + i_data [7:0] $end
       $var wire 3 F o_pos_one [2:0] $end
       $var wire 1 G o_zero_flag $end
       $var wire 1 J w_zero_flag_0 $end
       $var wire 2 K w_pos_one_0 [1:0] $end
       $var wire 1 L w_zero_flag_1 $end
       $var wire 2 M w_pos_one_1 [1:0] $end
       $scope module LOPD_4bit_unit_0 $end
        $var wire 4 , i_data [3:0] $end
        $var wire 2 K o_pos_one [1:0] $end
        $var wire 1 J o_zero_flag $end
       $upscope $end
       $scope module LOPD_4bit_unit_1 $end
        $var wire 4 - i_data [3:0] $end
        $var wire 2 M o_pos_one [1:0] $end
        $var wire 1 L o_zero_flag $end
       $upscope $end
      $upscope $end
      $scope module LOPD_8bit_unit_1 $end
       $var wire 8 . i_data [7:0] $end
       $var wire 3 H o_pos_one [2:0] $end
       $var wire 1 I o_zero_flag $end
       $var wire 1 N w_zero_flag_0 $end
       $var wire 2 O w_pos_one_0 [1:0] $end
       $var wire 1 P w_zero_flag_1 $end
       $var wire 2 Q w_pos_one_1 [1:0] $end
       $scope module LOPD_4bit_unit_0 $end
        $var wire 4 / i_data [3:0] $end
        $var wire 2 O o_pos_one [1:0] $end
        $var wire 1 N o_zero_flag $end
       $upscope $end
       $scope module LOPD_4bit_unit_1 $end
        $var wire 4 0 i_data [3:0] $end
        $var wire 2 Q o_pos_one [1:0] $end
        $var wire 1 P o_zero_flag $end
       $upscope $end
      $upscope $end
     $upscope $end
     $scope module LOPD_8bit_UNIT_MSB $end
      $var wire 8 ( i_data [7:0] $end
      $var wire 3 @ o_pos_one [2:0] $end
      $var wire 1 A o_zero_flag $end
      $var wire 1 B w_zero_flag_0 $end
      $var wire 2 C w_pos_one_0 [1:0] $end
      $var wire 1 D w_zero_flag_1 $end
      $var wire 2 E w_pos_one_1 [1:0] $end
      $scope module LOPD_4bit_unit_0 $end
       $var wire 4 ) i_data [3:0] $end
       $var wire 2 C o_pos_one [1:0] $end
       $var wire 1 B o_zero_flag $end
      $upscope $end
      $scope module LOPD_4bit_unit_1 $end
       $var wire 4 * i_data [3:0] $end
       $var wire 2 E o_pos_one [1:0] $end
       $var wire 1 D o_zero_flag $end
      $upscope $end
     $upscope $end
    $upscope $end
   $upscope $end
  $upscope $end
 $upscope $end
$enddefinitions $end


#0
0#
b000000000000000000000000 $
b000000000000000000000000 %
b00000000000000000000000000000000 &
b0000000000000000 '
b00000000 (
b0000 )
b0000 *
b00000000 +
b0000 ,
b0000 -
b00000000 .
b0000 /
b0000 0
b000000000000000000000000 1
b00000 2
03
b00000000000000000000000000000000 4
b00000 5
16
b0000 7
18
b0000 9
1:
0;
b00000 <
1=
b0000 >
1?
b000 @
1A
1B
b00 C
1D
b00 E
b000 F
1G
b000 H
1I
1J
b00 K
1L
b00 M
1N
b00 O
1P
b00 Q
b0000000000000000 R
b000 S
1T
b000 U
1V
b00000000 W
1X
b00 Y
1Z
b00 [
b0000 \
b0000 ]
b00000000 ^
1_
b00 `
1a
b00 b
b0000 c
b0000 d
b0000000000000000 e
b000 f
1g
b000 h
1i
b00000000 j
1k
b00 l
1m
b00 n
b0000 o
b0000 p
b00000000 q
1r
b00 s
1t
b00 u
b0000 v
b0000 w
b00000000000000000000000000011000 x
b00000000000000000000000000000101 y
b000000000000000000000000 z
#5000
1;
#10000
0;
#15000
1;
#20000
1#
0;
#25000
13
1;
#30000
b00000000000000000000000000000001 &
0;
#31000
b000000000000000000000001 $
b000000000000000000000001 %
b0000000000000001 '
b00000001 +
b0001 ,
0=
0?
0G
0J
#35000
b00000000000000000000000000000010 &
b000000000000000000000001 1
03
1;
#36000
b000000000000000000000010 $
b000000000000000000000010 %
b0000000000000010 '
b00000010 +
b0010 ,
b00001 <
b0001 >
b001 F
b01 K
#40000
0;
#45000
b00000000000000000000000000000100 &
b000000000000000000000010 1
b00001 2
1;
#46000
b000000000000000000000011 $
b000000000000000000000100 %
b0000000000000100 '
b00000100 +
b0100 ,
b00010 <
b0010 >
b010 F
b10 K
#50000
0;
#55000
b00000000000000000000000000001000 &
b000000000000000000000011 1
b00010 2
1;
#56000
b000000000000000000000100 $
b000000000000000000001000 %
b0000000000001000 '
b00001000 +
b1000 ,
b00011 <
b0011 >
b011 F
b11 K
#60000
0;
#65000
b00000000000000000000000000010000 &
b000000000000000000000100 1
b00011 2
1;
#66000
b000000000000000000000101 $
b000000000000000000010000 %
b0000000000010000 '
b00010000 +
b0000 ,
b0001 -
b00100 <
b0100 >
b100 F
1J
b00 K
0L
#70000
0;
#75000
b00000000000000000000000000100000 &
b000000000000000000000101 1
b00100 2
1;
#76000
b000000000000000000000110 $
b000000000000000000100000 %
b0000000000100000 '
b00100000 +
b0010 -
b00101 <
b0101 >
b101 F
b01 M
#80000
0;
#85000
b00000000000000000000000001000000 &
b000000000000000000000110 1
b00101 2
1;
#86000
b000000000000000000000111 $
b000000000000000001000000 %
b0000000001000000 '
b01000000 +
b0100 -
b00110 <
b0110 >
b110 F
b10 M
#90000
0;
#95000
b00000000000000000000000010000000 &
b000000000000000000000111 1
b00110 2
1;
#96000
b000000000000000000001000 $
b000000000000000010000000 %
b0000000010000000 '
b10000000 +
b1000 -
b00111 <
b0111 >
b111 F
b11 M
#100000
0;
#105000
b00000000000000000000000100000000 &
b000000000000000000001000 1
b00111 2
1;
#106000
b000000000000000000001001 $
b000000000000000100000000 %
b0000000100000000 '
b00000000 +
b0000 -
b00000001 .
b0001 /
b01000 <
b1000 >
b000 F
1G
0I
1L
b00 M
0N
#110000
0;
#115000
b00000000000000000000001000000000 &
b000000000000000000001001 1
b01000 2
1;
#116000
b000000000000000000001010 $
b000000000000001000000000 %
b0000001000000000 '
b00000010 .
b0010 /
b01001 <
b1001 >
b001 H
b01 O
#120000
0;
#125000
b00000000000000000000010000000000 &
b000000000000000000001010 1
b01001 2
1;
#126000
b000000000000000000001011 $
b000000000000010000000000 %
b0000010000000000 '
b00000100 .
b0100 /
b01010 <
b1010 >
b010 H
b10 O
#130000
0;
#135000
b00000000000000000000100000000000 &
b000000000000000000001011 1
b01010 2
1;
#136000
b000000000000000000001100 $
b000000000000100000000000 %
b0000100000000000 '
b00001000 .
b1000 /
b01011 <
b1011 >
b011 H
b11 O
#140000
0;
#145000
b00000000000000000001000000000000 &
b000000000000000000001100 1
b01011 2
1;
#146000
b000000000000000000001101 $
b000000000001000000000000 %
b0001000000000000 '
b00010000 .
b0000 /
b0001 0
b01100 <
b1100 >
b100 H
1N
b00 O
0P
#150000
0;
#155000
b00000000000000000010000000000000 &
b000000000000000000001101 1
b01100 2
1;
#156000
b000000000000000000001110 $
b000000000010000000000000 %
b0010000000000000 '
b00100000 .
b0010 0
b01101 <
b1101 >
b101 H
b01 Q
#160000
0;
#165000
b00000000000000000100000000000000 &
b000000000000000000001110 1
b01101 2
1;
#166000
b000000000000000000001111 $
b000000000100000000000000 %
b0100000000000000 '
b01000000 .
b0100 0
b01110 <
b1110 >
b110 H
b10 Q
#170000
0;
#175000
b00000000000000001000000000000000 &
b000000000000000000001111 1
b01110 2
1;
#176000
b000000000000000000010000 $
b000000001000000000000000 %
b1000000000000000 '
b10000000 .
b1000 0
b01111 <
b1111 >
b111 H
b11 Q
#180000
0;
#185000
b00000000000000010000000000000000 &
b000000000000000000010000 1
b01111 2
1;
#186000
b000000000000000000010001 $
b000000010000000000000000 %
b0000000000000000 '
b00000001 (
b0001 )
b00000000 .
b0000 0
b10000 <
b0000 >
1?
0A
0B
b000 H
1I
1P
b00 Q
#190000
0;
#195000
b00000000000000100000000000000000 &
b000000000000000000010001 1
b10000 2
1;
#196000
b000000000000000000010010 $
b000000100000000000000000 %
b00000010 (
b0010 )
b10001 <
b001 @
b01 C
#200000
0;
#205000
b00000000000001000000000000000000 &
b000000000000000000010010 1
b10001 2
1;
#206000
b000000000000000000010011 $
b000001000000000000000000 %
b00000100 (
b0100 )
b10010 <
b010 @
b10 C
#210000
0;
#215000
b00000000000010000000000000000000 &
b000000000000000000010011 1
b10010 2
1;
#216000
b000000000000000000010100 $
b000010000000000000000000 %
b00001000 (
b1000 )
b10011 <
b011 @
b11 C
#220000
0;
#225000
b00000000000100000000000000000000 &
b000000000000000000010100 1
b10011 2
1;
#226000
b000000000000000000010101 $
b000100000000000000000000 %
b00010000 (
b0000 )
b0001 *
b10100 <
b100 @
1B
b00 C
0D
#230000
0;
#235000
b00000000001000000000000000000000 &
b000000000000000000010101 1
b10100 2
1;
#236000
b000000000000000000010110 $
b001000000000000000000000 %
b00100000 (
b0010 *
b10101 <
b101 @
b01 E
#240000
0;
#245000
b00000000010000000000000000000000 &
b000000000000000000010110 1
b10101 2
1;
#246000
b000000000000000000010111 $
b010000000000000000000000 %
b01000000 (
b0100 *
b10110 <
b110 @
b10 E
#250000
0;
#255000
b00000000100000000000000000000000 &
b000000000000000000010111 1
b10110 2
1;
#256000
b000000000000000000011000 $
b100000000000000000000000 %
b10000000 (
b1000 *
b10111 <
b111 @
b11 E
#260000
0;
#265000
b00000001000000000000000000000000 &
b000000000000000000011000 1
b10111 2
1;
#266000
b000000000000000000011001 $
b000100000000000000000000 %
b00000000000000000000000000010100 &
b00010000 (
b0001 *
b10100 <
b100 @
b00 E
#270000
0;
#275000
b000000000000000000011001 1
b10100 2
1;
#276000
b000000000000000000011010 $
b000000000000000000000100 %
b00000000000000000000000000000010 &
b0000000000000100 '
b00000000 (
b0000 *
b00000100 +
b0100 ,
b00010 <
b0010 >
0?
b000 @
1A
1D
b010 F
0G
0J
b10 K
#280000
0;
#285000
b000000000000000000011010 1
b00010 2
1;
#286000
b000000000000000000011011 $
b000000000000000000000001 %
b00000000000000000000000000000000 &
b0000000000000001 '
b00000001 +
b0001 ,
b00000 <
b0000 >
b000 F
b00 K
#290000
0;
#295000
b000000000000000000011011 1
b00000 2
1;
#296000
b000000000000000000011100 $
b010000000000000000000000 %
b00000000000000000000000000010110 &
b0000000000000000 '
b01000000 (
b0100 *
b00000000 +
b0000 ,
b10110 <
1?
b110 @
0A
0D
b10 E
1G
1J
#300000
0;
#305000
b000000000000000000011100 1
b10110 2
1;
#306000
b000000000000000000011101 $
b100111100001011110100001 %
b00000000000000000000000000000111 &
b0001011110100001 '
b10011110 (
b1110 )
b1001 *
b10100001 +
b0001 ,
b1010 -
b00010111 .
b0111 /
b0001 0
b10111 <
b1100 >
0?
b111 @
0B
b11 C
b11 E
b111 F
0G
b100 H
0I
0J
0L
b11 M
0N
b10 O
0P
#310000
0;
#315000
b000000000000000000011101 1
b10111 2
1;
#316000
b000000000000000000011110 $
b010100111111001110000010 %
b00000000000000000000000000010001 &
b1111001110000010 '
b01010011 (
b0011 )
b0101 *
b10000010 +
b0010 ,
b1000 -
b11110011 .
b0011 /
b1111 0
b10110 <
b1111 >
b110 @
b01 C
b10 E
b111 H
b01 K
b01 O
b11 Q
#320000
0;
#325000
b000000000000000000011110 1
b10110 2
1;
#326000
b000000000000000000011111 $
b111110111100110100010010 %
b00000000000000000000000000001010 &
b1100110100010010 '
b11111011 (
b1011 )
b1111 *
b00010010 +
b0001 -
b11001101 .
b1101 /
b1100 0
b10111 <
b111 @
b11 C
b11 E
b100 F
b00 M
b11 O
#330000
0;
#335000
b000000000000000000011111 1
b10111 2
1;
#336000
b000000000000000000100000 $
b011010110100000111110100 %
b00000000000000000000000000001110 &
b0100000111110100 '
b01101011 (
b0110 *
b11110100 +
b0100 ,
b1111 -
b01000001 .
b0001 /
b0100 0
b10110 <
b1110 >
b110 @
b10 E
b111 F
b110 H
b10 K
b11 M
b00 O
b10 Q
#340000
0;
#345000
b000000000000000000100000 1
b10110 2
1;
#346000
b000000000000000000100001 $
b000000000000100000000000 %
b00000000000000000000000000001011 &
b0000100000000000 '
b00000000 (
b0000 )
b0000 *
b00000000 +
b0000 ,
b0000 -
b00001000 .
b1000 /
b0000 0
b01011 <
b1011 >
b000 @
1A
1B
b00 C
1D
b00 E
b000 F
1G
b011 H
1J
b00 K
1L
b00 M
b11 O
1P
b00 Q
#350000
0;
#355000
b000000000000000000100001 1
b01011 2
1;
#356000
b000000000000000000100010 $
b000000000000000000000100 %
b00000000000000000000000000000010 &
b0000000000000100 '
b00000100 +
b0100 ,
b00000000 .
b0000 /
b00010 <
b0010 >
b010 F
0G
b000 H
1I
0J
b10 K
1N
b00 O
#360000
0;
#365000
b000000000000000000100010 1
b00010 2
1;
