02_rtl/Question2/LOPD_4bit.sv
module LOPD_4bit(
    input logic [3:0]       i_data  ,
    output logic [1:0]      o_pos_one,
    output logic            o_zero_flag
);

/////////////////// LDO ///////////////////
// D[3] | D[2] | D[1] | D[0] |PO[3] | PO[2] | PO[1] | PO[0] | ZERO_FLAG |
//   0  |   0  |   0  |   0  |  0   |   0   |   0   |   0   |     1     |
//   0  |   0  |   0  |   1  |  0   |   0   |   0   |   1   |     0     |
//   0  |   0  |   1  |   X  |  0   |   0   |   1   |   0   |     0     |
//   0  |   1  |   X  |   X  |  0   |   1   |   0   |   0   |     0     |
//   1  |   X  |   X  |   X  |  1   |   0   |   0   |   0   |     0     |
/////////////////// LDOD ///////////////////
// D[3] | D[2] | D[1] | D[0] | PO[1] | PO[0] | ZERO_FLAG |
//   0  |   0  |   0  |   0  |   0   |   0   |     1     |
//   0  |   0  |   0  |   1  |   0   |   0   |     0     |
//   0  |   0  |   1  |   X  |   0   |   1   |     0     |
//   0  |   1  |   X  |   X  |   1   |   0   |     0     |
//   1  |   X  |   X  |   X  |   1   |   1   |     0     |

assign o_zero_flag = ~((o_pos_one[1])|(i_data[1]|i_data[0])) ;
assign o_pos_one[1] = i_data[3] | i_data[2];
assign o_pos_one[0] = ((~(i_data[3] | i_data[2])) & (i_data[1])) |  (i_data[3]);

endmodule

02_rtl/Question2/LOPD_8bit.sv
module LOPD_8bit(
    input logic [7:0]       i_data  ,
    output logic [2:0]      o_pos_one,
    output logic            o_zero_flag
);

////////////////////////////////////////////////////////////
// LOPD_4bit_unit_0
////////////////////////////////////////////////////////////
logic w_zero_flag_0;
logic [1:0] w_pos_one_0;
LOPD_4bit LOPD_4bit_unit_0 (
    .i_data         (i_data[3:0]),
    .o_pos_one      (w_pos_one_0),
    .o_zero_flag    (w_zero_flag_0)
);

////////////////////////////////////////////////////////////
// LOPD_4bit_unit_1
////////////////////////////////////////////////////////////
logic w_zero_flag_1;
logic [1:0] w_pos_one_1;
LOPD_4bit LOPD_4bit_unit_1 (
    .i_data         (i_data[7:4]),
    .o_pos_one      (w_pos_one_1),
    .o_zero_flag    (w_zero_flag_1)
);

////////////////////////////////////////////////////////////
// LOD_8bit_unit
////////////////////////////////////////////////////////////
assign o_zero_flag = w_zero_flag_0 & w_zero_flag_1;
assign o_pos_one[2] = ~(w_zero_flag_1);
assign o_pos_one[1] = (w_zero_flag_1) ? w_pos_one_0[1] : w_pos_one_1[1];
assign o_pos_one[0] = (w_zero_flag_1) ? w_pos_one_0[0] : w_pos_one_1[0];

endmodule

02_rtl/Question2/LOPD_16bit.sv
module LOPD_16bit(
    input logic [15:0]       i_data  ,
    output logic [3:0]      o_pos_one,
    output logic            o_zero_flag
);


////////////////////////////////////////////////////////////
// LOPD_8bit_unit_0
////////////////////////////////////////////////////////////
logic [2:0]         w_pos_one_0;  
logic               w_zero_flag_0;
LOPD_8bit LOPD_8bit_unit_0(
    .i_data         (i_data[7:0]),
    .o_pos_one      (w_pos_one_0),
    .o_zero_flag    (w_zero_flag_0)
);
////////////////////////////////////////////////////////////
// LOPD_8bit_unit_1
////////////////////////////////////////////////////////////
logic [2:0]         w_pos_one_1;  
logic               w_zero_flag_1;
LOPD_8bit LOPD_8bit_unit_1(
    .i_data         (i_data[15:8]),
    .o_pos_one      (w_pos_one_1),
    .o_zero_flag    (w_zero_flag_1)
);

////////////////////////////////////////////////////////////
// LOD_16bit_unit
////////////////////////////////////////////////////////////
assign o_zero_flag = w_zero_flag_0 & w_zero_flag_1;
assign o_pos_one[3] = ~(w_zero_flag_1);
assign o_pos_one[2] = w_zero_flag_1 ? w_pos_one_0[2] : w_pos_one_1[2];
assign o_pos_one[1] = w_zero_flag_1 ? w_pos_one_0[1] : w_pos_one_1[1];
assign o_pos_one[0] = w_zero_flag_1 ? w_pos_one_0[0] : w_pos_one_1[0];
endmodule

03_verif/Question2/coverage/annotated_src/Question2.sv
//      // verilator_coverage annotation
        module Question2 #(
            parameter SIZE_DATA     = 24    ,
            parameter SIZE_LOPD     = 5      
        )(
 000376     input logic [SIZE_DATA-1:0]     i_data          ,
 000282     output logic [SIZE_LOPD-1:0]    o_one_position  ,
%000002     output logic                    o_zero_flag      
        );
        
 000376 logic [15:0]     LOPD16_i_data;
        assign LOPD16_i_data = i_data[15:0];
 000440 logic [3:0]      LOPD16_o_pos_one;
 000297 logic            LOPD16_o_zero_flag;
 000385 logic [7:0]      LOPD8_i_data;
        assign LOPD8_i_data = i_data[23:16];
 000474 logic [2:0]      LOPD8_o_pos_one;
 000434 logic            LOPD8_o_zero_flag;
        LOPD_16bit LOPD_16bit_UNIT_LSB (
            .i_data             (LOPD16_i_data),
            .o_pos_one          (LOPD16_o_pos_one),
            .o_zero_flag        (LOPD16_o_zero_flag)
        );
        
        LOPD_8bit LOPD_8bit_UNIT_MSB (
            .i_data             (LOPD8_i_data),
            .o_pos_one          (LOPD8_o_pos_one),
            .o_zero_flag        (LOPD8_o_zero_flag)
        );
        
        assign o_zero_flag = LOPD16_o_zero_flag & LOPD8_o_zero_flag;
        assign o_one_position[4] = ~LOPD8_o_zero_flag;
        assign o_one_position[3] = LOPD8_o_zero_flag ? LOPD16_o_pos_one[3] : 1'b0;
        assign o_one_position[2] = LOPD8_o_zero_flag ? LOPD16_o_pos_one[2] : LOPD8_o_pos_one[2];
        assign o_one_position[1] = LOPD8_o_zero_flag ? LOPD16_o_pos_one[1] : LOPD8_o_pos_one[1];
        assign o_one_position[0] = LOPD8_o_zero_flag ? LOPD16_o_pos_one[0] : LOPD8_o_pos_one[0];
        
        endmodule

03_verif/Question2/tb_Question2.sv
`timescale 1ns/1ps
module tb_Question2();

parameter SIZE_DATA = 24;
parameter SIZE_LOP  = 5;

int test_count = 0;
int test_pass  = 0;

logic i_clk, i_rst_n;
logic [SIZE_DATA-1:0] i_addr;
logic [SIZE_DATA-1:0] i_data;
logic [SIZE_DATA-1:0] o_addr;  
logic [SIZE_LOP-1:0]  o_one_position;
logic                 o_zero_flag;

function automatic logic [SIZE_LOP-1:0] Test_LOPD(
    input logic [SIZE_DATA-1:0]     f_i_data
);
    logic [SIZE_DATA-1:0] t_temp;
    int cnt_position_1;
    begin
        t_temp = f_i_data;
        cnt_position_1 = 0;

        if(t_temp == 0) begin
            Test_LOPD = '0;
        end else begin
            while (t_temp[SIZE_DATA-1] == 0) begin
                t_temp = t_temp << 1;
                cnt_position_1 ++;
            end
            Test_LOPD = SIZE_DATA - cnt_position_1 - 1;
        end
    end

endfunction

//===================== DUT =====================//
// Question2_unit #(
//     .SIZE_DATA (SIZE_DATA),
//     .SIZE_LOP  (SIZE_LOP)
// ) DUT (
//     .i_clk          (i_clk),
//     .i_rst_n        (i_rst_n),
//     .i_addr         (i_addr),
//     .i_data         (i_data),
//     .o_addr         (o_addr),
//     .o_one_position (o_one_position),
//     .o_zero_flag    (o_zero_flag)
// );
Question2 #(
    .SIZE_DATA (SIZE_DATA),
    .SIZE_LOPD  (SIZE_LOP)
) DUT (
    .i_data         (i_data),
    .o_one_position (o_one_position),
    .o_zero_flag    (o_zero_flag)
);
// scoreboard #(
//     .SIZE_DATA  (5)
// ) SCOREBOARD_UNIT (
//     .is_finish       (),
//     .i_expect_data   (),
//     .i_data_out      () 
// );

//===================== CLOCK =====================//
initial begin
    i_clk = 0;
    forever #5 i_clk = ~i_clk; // 10ns period = 100MHz
end

//===================== DUMP WAVE =====================//
initial begin
    $dumpfile("tb_Question2.vcd");
    $dumpvars(0, tb_Question2);
end
int bit_pos;
//===================== TEST SEQUENCE =====================//
initial begin
    i_rst_n = 0;
    i_addr  = '0;
    i_data  = '0;

    // Reset phase
    #20;
    i_rst_n = 1;
    #10;

    // Random test 100 lần
    bit_pos = 1;
    repeat (24) begin
        @(posedge i_clk);
        #1;
        i_addr = i_addr + 1;
        i_data  = bit_pos;
        #5;
        $display("=> i_data = %b (%d) \t| o_one_position = %b (%d) \t| o_zero_flag = %b", i_data, i_data, o_one_position, o_one_position, o_zero_flag);
        $display("[TIME: %5t] [%s] - %4s: Expect: %8h, DUT: %8h ", $time, "Direcly", (Test_LOPD(i_data) == o_one_position) ? "PASS" : "FAIL", o_one_position, Test_LOPD(i_data));
        test_count = test_count + 1;
        test_pass  = (Test_LOPD(i_data) == o_one_position) ? test_pass + 1 : test_pass;
        // @(posedge i_clk);
        bit_pos = bit_pos << 1'b1;
    end
    repeat (1000) begin
        @(posedge i_clk);
        #1;
        bit_pos = $urandom_range(0, SIZE_DATA-1);
        i_data = 24'b1 << bit_pos;
        if ($urandom_range(0, 1)) begin
            i_data |= $urandom_range(0, (1 << SIZE_DATA) - 1);
        end
        #5;
        $display("=> i_data = %b (%d) \t| o_one_position = %b (%d) \t| o_zero_flag = %b", i_data, i_data, o_one_position, o_one_position, o_zero_flag);
        $display("[TIME: %5t] [%s] - %4s: Expect: %8h, DUT: %8h ", $time, "Randome", (Test_LOPD(i_data) == o_one_position) ? "PASS" : "FAIL", o_one_position, Test_LOPD(i_data));
        test_count = test_count + 1;
        test_pass  = (Test_LOPD(i_data) == o_one_position) ? test_pass + 1 : test_pass;
        i_addr = i_addr + 1;
    end

    #10;
    $display("\n================================");
    $display("==========TEST SUMMARY==========");
    $display("Total test cases: %6d    ", test_count);
    $display("Passed          : %6d    ", test_pass);
    $display("Failed          : %6d    ", test_count - test_pass);
    $display("Pass rate       : %0.2f%%", (test_pass * 100.0) / (test_count));
    $display("================================");
    #100;

    $finish;
end

endmodule

03_verif/Question2/tb_Question2.vcd
$version Generated by VerilatedVcd $end
$timescale 1ps $end
 $scope module TOP $end
  $scope module tb_Question2 $end
   $var wire 32 J SIZE_DATA [31:0] $end
   $var wire 32 K SIZE_LOP [31:0] $end
   $var wire 32 # test_count [31:0] $end
   $var wire 32 $ test_pass [31:0] $end
   $var wire 1 I i_clk $end
   $var wire 1 % i_rst_n $end
   $var wire 24 & i_addr [23:0] $end
   $var wire 24 ' i_data [23:0] $end
   $var wire 24 L o_addr [23:0] $end
   $var wire 5 3 o_one_position [4:0] $end
   $var wire 1 4 o_zero_flag $end
   $var wire 32 ( bit_pos [31:0] $end
   $scope module DUT $end
    $var wire 32 J SIZE_DATA [31:0] $end
    $var wire 32 K SIZE_LOPD [31:0] $end
    $var wire 24 ' i_data [23:0] $end
    $var wire 5 3 o_one_position [4:0] $end
    $var wire 1 4 o_zero_flag $end
    $var wire 16 ) LOPD16_i_data [15:0] $end
    $var wire 4 5 LOPD16_o_pos_one [3:0] $end
    $var wire 1 6 LOPD16_o_zero_flag $end
    $var wire 8 * LOPD8_i_data [7:0] $end
    $var wire 3 7 LOPD8_o_pos_one [2:0] $end
    $var wire 1 8 LOPD8_o_zero_flag $end
    $scope module LOPD_16bit_UNIT_LSB $end
     $var wire 16 ) i_data [15:0] $end
     $var wire 4 5 o_pos_one [3:0] $end
     $var wire 1 6 o_zero_flag $end
     $var wire 3 9 w_pos_one_0 [2:0] $end
     $var wire 1 : w_zero_flag_0 $end
     $var wire 3 ; w_pos_one_1 [2:0] $end
     $var wire 1 < w_zero_flag_1 $end
     $scope module LOPD_8bit_unit_0 $end
      $var wire 8 + i_data [7:0] $end
      $var wire 3 9 o_pos_one [2:0] $end
      $var wire 1 : o_zero_flag $end
      $var wire 1 = w_zero_flag_0 $end
      $var wire 2 > w_pos_one_0 [1:0] $end
      $var wire 1 ? w_zero_flag_1 $end
      $var wire 2 @ w_pos_one_1 [1:0] $end
      $scope module LOPD_4bit_unit_0 $end
       $var wire 4 , i_data [3:0] $end
       $var wire 2 > o_pos_one [1:0] $end
       $var wire 1 = o_zero_flag $end
      $upscope $end
      $scope module LOPD_4bit_unit_1 $end
       $var wire 4 - i_data [3:0] $end
       $var wire 2 @ o_pos_one [1:0] $end
       $var wire 1 ? o_zero_flag $end
      $upscope $end
     $upscope $end
     $scope module LOPD_8bit_unit_1 $end
      $var wire 8 . i_data [7:0] $end
      $var wire 3 ; o_pos_one [2:0] $end
      $var wire 1 < o_zero_flag $end
      $var wire 1 A w_zero_flag_0 $end
      $var wire 2 B w_pos_one_0 [1:0] $end
      $var wire 1 C w_zero_flag_1 $end
      $var wire 2 D w_pos_one_1 [1:0] $end
      $scope module LOPD_4bit_unit_0 $end
       $var wire 4 / i_data [3:0] $end
       $var wire 2 B o_pos_one [1:0] $end
       $var wire 1 A o_zero_flag $end
      $upscope $end
      $scope module LOPD_4bit_unit_1 $end
       $var wire 4 0 i_data [3:0] $end
       $var wire 2 D o_pos_one [1:0] $end
       $var wire 1 C o_zero_flag $end
      $upscope $end
     $upscope $end
    $upscope $end
    $scope module LOPD_8bit_UNIT_MSB $end
     $var wire 8 * i_data [7:0] $end
     $var wire 3 7 o_pos_one [2:0] $end
     $var wire 1 8 o_zero_flag $end
     $var wire 1 E w_zero_flag_0 $end
     $var wire 2 F w_pos_one_0 [1:0] $end
     $var wire 1 G w_zero_flag_1 $end
     $var wire 2 H w_pos_one_1 [1:0] $end
     $scope module LOPD_4bit_unit_0 $end
      $var wire 4 1 i_data [3:0] $end
      $var wire 2 F o_pos_one [1:0] $end
      $var wire 1 E o_zero_flag $end
     $upscope $end
     $scope module LOPD_4bit_unit_1 $end
      $var wire 4 2 i_data [3:0] $end
      $var wire 2 H o_pos_one [1:0] $end
      $var wire 1 G o_zero_flag $end
     $upscope $end
    $upscope $end
   $upscope $end
  $upscope $end
 $upscope $end
$enddefinitions $end


#0
b00000000000000000000000000000000 #
b00000000000000000000000000000000 $
0%
b000000000000000000000000 &
b000000000000000000000000 '
b00000000000000000000000000000000 (
b0000000000000000 )
b00000000 *
b00000000 +
b0000 ,
b0000 -
b00000000 .
b0000 /
b0000 0
b0000 1
b0000 2
b00000 3
14
b0000 5
16
b000 7
18
b000 9
1:
b000 ;
1<
1=
b00 >
1?
b00 @
1A
b00 B
1C
b00 D
1E
b00 F
1G
b00 H
0I
b00000000000000000000000000011000 J
b00000000000000000000000000000101 K
b000000000000000000000000 L
#5000
1I
#10000
0I
#15000
1I
#20000
1%
0I
#25000
1I
#30000
b00000000000000000000000000000001 (
0I
#35000
1I
#36000
b000000000000000000000001 &
b000000000000000000000001 '
b0000000000000001 )
b00000001 +
b0001 ,
04
06
0:
0=
#40000
0I
#41000
b00000000000000000000000000000001 #
b00000000000000000000000000000001 $
b00000000000000000000000000000010 (
#45000
1I
#46000
b000000000000000000000010 &
b000000000000000000000010 '
b0000000000000010 )
b00000010 +
b0010 ,
b00001 3
b0001 5
b001 9
b01 >
#50000
0I
#51000
b00000000000000000000000000000010 #
b00000000000000000000000000000010 $
b00000000000000000000000000000100 (
#55000
1I
#56000
b000000000000000000000011 &
b000000000000000000000100 '
b0000000000000100 )
b00000100 +
b0100 ,
b00010 3
b0010 5
b010 9
b10 >
#60000
0I
#61000
b00000000000000000000000000000011 #
b00000000000000000000000000000011 $
b00000000000000000000000000001000 (
#65000
1I
#66000
b000000000000000000000100 &
b000000000000000000001000 '
b0000000000001000 )
b00001000 +
b1000 ,
b00011 3
b0011 5
b011 9
b11 >
#70000
0I
#71000
b00000000000000000000000000000100 #
b00000000000000000000000000000100 $
b00000000000000000000000000010000 (
#75000
1I
#76000
b000000000000000000000101 &
b000000000000000000010000 '
b0000000000010000 )
b00010000 +
b0000 ,
b0001 -
b00100 3
b0100 5
b100 9
1=
b00 >
0?
#80000
0I
#81000
b00000000000000000000000000000101 #
b00000000000000000000000000000101 $
b00000000000000000000000000100000 (
#85000
1I
#86000
b000000000000000000000110 &
b000000000000000000100000 '
b0000000000100000 )
b00100000 +
b0010 -
b00101 3
b0101 5
b101 9
b01 @
#90000
0I
#91000
b00000000000000000000000000000110 #
b00000000000000000000000000000110 $
b00000000000000000000000001000000 (
#95000
1I
#96000
b000000000000000000000111 &
b000000000000000001000000 '
b0000000001000000 )
b01000000 +
b0100 -
b00110 3
b0110 5
b110 9
b10 @
#100000
0I
#101000
b00000000000000000000000000000111 #
b00000000000000000000000000000111 $
b00000000000000000000000010000000 (
#105000
1I
#106000
b000000000000000000001000 &
b000000000000000010000000 '
b0000000010000000 )
b10000000 +
b1000 -
b00111 3
b0111 5
b111 9
b11 @
#110000
0I
#111000
b00000000000000000000000000001000 #
b00000000000000000000000000001000 $
b00000000000000000000000100000000 (
#115000
1I
#116000
b000000000000000000001001 &
b000000000000000100000000 '
b0000000100000000 )
b00000000 +
b0000 -
b00000001 .
b0001 /
b01000 3
b1000 5
b000 9
1:
0<
1?
b00 @
0A
#120000
0I
#121000
b00000000000000000000000000001001 #
b00000000000000000000000000001001 $
b00000000000000000000001000000000 (
#125000
1I
#126000
b000000000000000000001010 &
b000000000000001000000000 '
b0000001000000000 )
b00000010 .
b0010 /
b01001 3
b1001 5
b001 ;
b01 B
#130000
0I
#131000
b00000000000000000000000000001010 #
b00000000000000000000000000001010 $
b00000000000000000000010000000000 (
#135000
1I
#136000
b000000000000000000001011 &
b000000000000010000000000 '
b0000010000000000 )
b00000100 .
b0100 /
b01010 3
b1010 5
b010 ;
b10 B
#140000
0I
#141000
b00000000000000000000000000001011 #
b00000000000000000000000000001011 $
b00000000000000000000100000000000 (
#145000
1I
#146000
b000000000000000000001100 &
b000000000000100000000000 '
b0000100000000000 )
b00001000 .
b1000 /
b01011 3
b1011 5
b011 ;
b11 B
#150000
0I
#151000
b00000000000000000000000000001100 #
b00000000000000000000000000001100 $
b00000000000000000001000000000000 (
#155000
1I
#156000
b000000000000000000001101 &
b000000000001000000000000 '
b0001000000000000 )
b00010000 .
b0000 /
b0001 0
b01100 3
b1100 5
b100 ;
1A
b00 B
0C
#160000
0I
#161000
b00000000000000000000000000001101 #
b00000000000000000000000000001101 $
b00000000000000000010000000000000 (
#165000
1I
#166000
b000000000000000000001110 &
b000000000010000000000000 '
b0010000000000000 )
b00100000 .
b0010 0
b01101 3
b1101 5
b101 ;
b01 D
#170000
0I
#171000
b00000000000000000000000000001110 #
b00000000000000000000000000001110 $
b00000000000000000100000000000000 (
#175000
1I
#176000
b000000000000000000001111 &
b000000000100000000000000 '
b0100000000000000 )
b01000000 .
b0100 0
b01110 3
b1110 5
b110 ;
b10 D
#180000
0I
#181000
b00000000000000000000000000001111 #
b00000000000000000000000000001111 $
b00000000000000001000000000000000 (
#185000
1I
#186000
b000000000000000000010000 &
b000000001000000000000000 '
b1000000000000000 )
b10000000 .
b1000 0
b01111 3
b1111 5
b111 ;
b11 D
#190000
0I
#191000
b00000000000000000000000000010000 #
b00000000000000000000000000010000 $
b00000000000000010000000000000000 (
#195000
1I
#196000
b000000000000000000010001 &
b000000010000000000000000 '
b0000000000000000 )
b00000001 *
b00000000 .
b0000 0
b0001 1
b10000 3
b0000 5
16
08
b000 ;
1<
1C
b00 D
0E
#200000
0I
#201000
b00000000000000000000000000010001 #
b00000000000000000000000000010001 $
b00000000000000100000000000000000 (
#205000
1I
#206000
b000000000000000000010010 &
b000000100000000000000000 '
b00000010 *
b0010 1
b10001 3
b001 7
b01 F
#210000
0I
#211000
b00000000000000000000000000010010 #
b00000000000000000000000000010010 $
b00000000000001000000000000000000 (
#215000
1I
#216000
b000000000000000000010011 &
b000001000000000000000000 '
b00000100 *
b0100 1
b10010 3
b010 7
b10 F
#220000
0I
#221000
b00000000000000000000000000010011 #
b00000000000000000000000000010011 $
b00000000000010000000000000000000 (
#225000
1I
#226000
b000000000000000000010100 &
b000010000000000000000000 '
b00001000 *
b1000 1
b10011 3
b011 7
b11 F
#230000
0I
#231000
b00000000000000000000000000010100 #
b00000000000000000000000000010100 $
b00000000000100000000000000000000 (
#235000
1I
#236000
b000000000000000000010101 &
b000100000000000000000000 '
b00010000 *
b0000 1
b0001 2
b10100 3
b100 7
1E
b00 F
0G
#240000
0I
#241000
b00000000000000000000000000010101 #
b00000000000000000000000000010101 $
b00000000001000000000000000000000 (
#245000
1I
#246000
b000000000000000000010110 &
b001000000000000000000000 '
b00100000 *
b0010 2
b10101 3
b101 7
b01 H
#250000
0I
#251000
b00000000000000000000000000010110 #
b00000000000000000000000000010110 $
b00000000010000000000000000000000 (
#255000
1I
#256000
b000000000000000000010111 &
b010000000000000000000000 '
b01000000 *
b0100 2
b10110 3
b110 7
b10 H
#260000
0I
#261000
b00000000000000000000000000010111 #
b00000000000000000000000000010111 $
b00000000100000000000000000000000 (
#265000
1I
#266000
b000000000000000000011000 &
b100000000000000000000000 '
b10000000 *
b1000 2
b10111 3
b111 7
b11 H
#270000
0I
#271000
b00000000000000000000000000011000 #
b00000000000000000000000000011000 $
b00000001000000000000000000000000 (
#275000
1I
#276000
b000100000000000000000000 '
b00000000000000000000000000010100 (
b00010000 *
b0001 2
b10100 3
b100 7
b00 H
#280000
0I
#281000
b00000000000000000000000000011001 #
b00000000000000000000000000011001 $
b000000000000000000011001 &
#285000
1I
#286000
b000000000000000000000100 '
b00000000000000000000000000000010 (
b0000000000000100 )
b00000000 *
b00000100 +
b0100 ,
b0000 2
b00010 3
b0010 5
06
b000 7
18
b010 9
0:
0=
b10 >
1G
#290000
0I
#291000
b00000000000000000000000000011010 #
b00000000000000000000000000011010 $
b000000000000000000011010 &
#295000
1I
#296000
b000000000000000000000001 '
b00000000000000000000000000000000 (
b0000000000000001 )
b00000001 +
b0001 ,
b00000 3
b0000 5
b000 9
b00 >
#300000
0I
#301000
b00000000000000000000000000011011 #
b00000000000000000000000000011011 $
b000000000000000000011011 &
#305000
1I
#306000
b010000000000000000000000 '
b00000000000000000000000000010110 (
b0000000000000000 )
b01000000 *
b00000000 +
b0000 ,
b0100 2
b10110 3
16
b110 7
08
1:
1=
0G
b10 H
#310000
0I
#311000
b00000000000000000000000000011100 #
b00000000000000000000000000011100 $
b000000000000000000011100 &
#315000
1I
#316000
b100111100001011110100001 '
b00000000000000000000000000000111 (
b0001011110100001 )
b10011110 *
b10100001 +
b0001 ,
b1010 -
b00010111 .
b0111 /
b0001 0
b1110 1
b1001 2
b10111 3
b1100 5
06
b111 7
b111 9
0:
b100 ;
0<
0=
0?
b11 @
0A
b10 B
0C
0E
b11 F
b11 H
#320000
0I
#321000
b00000000000000000000000000011101 #
b00000000000000000000000000011101 $
b000000000000000000011101 &
#325000
1I
#326000
b010100111111001110000010 '
b00000000000000000000000000010001 (
b1111001110000010 )
b01010011 *
b10000010 +
b0010 ,
b1000 -
b11110011 .
b0011 /
b1111 0
b0011 1
b0101 2
b10110 3
b1111 5
b110 7
b111 ;
b01 >
b01 B
b11 D
b01 F
b10 H
#330000
0I
#331000
b00000000000000000000000000011110 #
b00000000000000000000000000011110 $
b000000000000000000011110 &
#335000
1I
#336000
b111110111100110100010010 '
b00000000000000000000000000001010 (
b1100110100010010 )
b11111011 *
b00010010 +
b0001 -
b11001101 .
b1101 /
b1100 0
b1011 1
b1111 2
b10111 3
b111 7
b100 9
b00 @
b11 B
b11 F
b11 H
#340000
0I
#341000
b00000000000000000000000000011111 #
b00000000000000000000000000011111 $
b000000000000000000011111 &
#345000
1I
#346000
b011010110100000111110100 '
b00000000000000000000000000001110 (
b0100000111110100 )
b01101011 *
b11110100 +
b0100 ,
b1111 -
b01000001 .
b0001 /
b0100 0
b0110 2
b10110 3
b1110 5
b110 7
b111 9
b110 ;
b10 >
b11 @
b00 B
b10 D
b10 H
#350000
0I
#351000
b00000000000000000000000000100000 #
b00000000000000000000000000100000 $
b000000000000000000100000 &
#355000
1I
#356000
b000000000000100000000000 '
b00000000000000000000000000001011 (
b0000100000000000 )
b00000000 *
b00000000 +
b0000 ,
b0000 -
b00001000 .
b1000 /
b0000 0
b0000 1
b0000 2
b01011 3
b1011 5
b000 7
18
b000 9
1:
b011 ;
1=
b00 >
1?
b00 @
b11 B
1C
b00 D
1E
b00 F
1G
b00 H
#360000
0I
#361000
b00000000000000000000000000100001 #
b00000000000000000000000000100001 $
b000000000000000000100001 &
#365000
1I
#366000
b000000000000000000000100 '
b00000000000000000000000000000010 (
b0000000000000100 )
b00000100 +
b0100 ,
b00000000 .
b0000 /
b00010 3
b0010 5
b010 9
0:
b000 ;
1<
0=
b10 >
1A
b00 B
#370000
0I
#371000
b00000000000000000000000000100010 #
b00000000000000000000000000100010 $
b000000000000000000100010 &
#375000
1I
#376000
b000000000000000001000000 '
b00000000000000000000000000000110 (
b0000000001000000 )
b01000000 +
b0000 ,
b0100 -
b00110 3
b0110 5
b110 9
1=
b00 >
0?
b10 @
#380000
0I
#381000
b00000000000000000000000000100011 #
b00000000000000000000000000100011 $
b000000000000000000100011 &
#385000
1I
#386000
#390000
0I
#391000
b00000000000000000000000000100100 #
b00000000000000000000000000100100 $
b000000000000000000100100 &
#395000
1I
#396000
b000000010000000000000000 '
b00000000000000000000000000010000 (
b0000000000000000 )
b00000001 *
b00000000 +
b0000 -
b0001 1
b10000 3
b0000 5
16
08
b000 9
1:
1?
b00 @
0E
#400000
0I
#401000
b00000000000000000000000000100101 #
b00000000000000000000000000100101 $
b000000000000000000100101 &
#405000
1I
#406000
b000000000000000000001000 '
b00000000000000000000000000000011 (
b0000000000001000 )
b00000000 *
b00001000 +
b1000 ,
b0000 1
b00011 3
b0011 5
06
18
b011 9
0:
0=
b11 >
1E
#410000
0I
#411000
b00000000000000000000000000100110 #
b00000000000000000000000000100110 $
b000000000000000000100110 &
#415000
1I
#416000
b000000000010000000000000 '
b00000000000000000000000000001101 (
b0010000000000000 )
b00000000 +
b0000 ,
b00100000 .
b0010 0
b01101 3
b1101 5
b000 9
1:
b101 ;
0<
1=
b00 >
0C
b01 D
#420000
0I
#421000
b00000000000000000000000000100111 #
b00000000000000000000000000100111 $
b000000000000000000100111 &
#425000
1I
#426000
b011011010011001001100011 '
b00000000000000000000000000010110 (
b0011001001100011 )
b01101101 *
b01100011 +
b0011 ,
b0110 -
b00110010 .
b0010 /
b0011 0
b1101 1
b0110 2
b10110 3
b110 7
08
b110 9
0:
0=
b01 >
0?
b10 @
0A
b01 B
0E
b11 F
0G
b10 H
#430000
0I
#431000
b00000000000000000000000000101000 #
b00000000000000000000000000101000 $
b000000000000000000101000 &
#435000
1I
#436000
b010101011101101011001110 '
b00000000000000000000000000010000 (
b1101101011001110 )
b01010101 *
b11001110 +
b1110 ,
b1100 -
b11011010 .
b1010 /
b1101 0
b0101 1
b0101 2
b1111 5
b111 9
b111 ;
b11 >
b11 @
b11 B
b11 D
b10 F
#440000
0I
#441000
b00000000000000000000000000101001 #
b00000000000000000000000000101001 $
b000000000000000000101001 &
#445000
1I
#446000
b110110011011001110011110 '
b00000000000000000000000000001111 (
b1011001110011110 )
b11011001 *
b10011110 +
b1001 -
b10110011 .
b0011 /
b1011 0
b1001 1
b1101 2
b10111 3
b111 7
b01 B
b11 F
b11 H
#450000
0I
#451000
b00000000000000000000000000101010 #
b00000000000000000000000000101010 $
b000000000000000000101010 &
#455000
1I
#456000
b000000001000000000000000 '
b1000000000000000 )
b00000000 *
b00000000 +
b0000 ,
b0000 -
b10000000 .
b0000 /
b1000 0
b0000 1
b0000 2
b01111 3
b000 7
18
b000 9
1:
1=
b00 >
1?
b00 @
1A
b00 B
1E
b00 F
1G
b00 H
#460000
0I
#461000
b00000000000000000000000000101011 #
b00000000000000000000000000101011 $
b000000000000000000101011 &
#465000
1I
#466000
b111100111001000010111011 '
b00000000000000000000000000010000 (
b1001000010111011 )
b11110011 *
b10111011 +
b1011 ,
b1011 -
b10010000 .
b1001 0
b0011 1
b1111 2
b10111 3
b111 7
08
b111 9
0:
0=
b11 >
0?
b11 @
0E
b01 F
0G
b11 H
#470000
0I
#471000
b00000000000000000000000000101100 #
b00000000000000000000000000101100 $
b000000000000000000101100 &
#475000
1I
#476000
b000100000000000000000000 '
b00000000000000000000000000010100 (
b0000000000000000 )
b00010000 *
b00000000 +
b0000 ,
b0000 -
b00000000 .
b0000 0
b0000 1
b0001 2
b10100 3
b0000 5
16
b100 7
b000 9
1:
b000 ;
1<
1=
b00 >
1?
b00 @
1C
b00 D
1E
b00 F
b00 H
#480000
0I
#481000
b00000000000000000000000000101101 #
b00000000000000000000000000101101 $
b000000000000000000101101 &
#485000
1I
#486000
b010101001011001101001001 '
b00000000000000000000000000000110 (
b1011001101001001 )
b01010100 *
b01001001 +
b1001 ,
b0100 -
b10110011 .
b0011 /
b1011 0
b0100 1
b0101 2
b10110 3
b1111 5
06
b110 7
b110 9
0:
b111 ;
0<
0=
b11 >
0?
b10 @
0A
b01 B
0C
b11 D
0E
b10 F
b10 H
#490000
0I
#491000
b00000000000000000000000000101110 #
b00000000000000000000000000101110 $
b000000000000000000101110 &
#495000
1I
#496000
b101011011010111110001100 '
b00000000000000000000000000000011 (
b1010111110001100 )
b10101101 *
b10001100 +
b1100 ,
b1000 -
b10101111 .
b1111 /
b1010 0
b1101 1
b1010 2
b10111 3
b111 7
b111 9
b11 @
b11 B
b11 F
b11 H
#500000
0I
#501000
b00000000000000000000000000101111 #
b00000000000000000000000000101111 $
b000000000000000000101111 &
#505000
1I
#506000
b011100101110101001101011 '
b00000000000000000000000000000101 (
b1110101001101011 )
b01110010 *
b01101011 +
b1011 ,
b0110 -
b11101010 .
b1010 /
b1110 0
b0010 1
b0111 2
b10110 3
b110 7
b110 9
b10 @
b01 F
b10 H
#510000
0I
#511000
b00000000000000000000000000110000 #
b00000000000000000000000000110000 $
b000000000000000000110000 &
#515000
1I
#516000
b101100110010110011001001 '
b00000000000000000000000000010100 (
b0010110011001001 )
b10110011 *
b11001001 +
b1001 ,
b1100 -
b00101100 .
b1100 /
b0010 0
b0011 1
b1011 2
b10111 3
b1101 5
b111 7
b111 9
b101 ;
b11 @
b01 D
b11 H
#520000
0I
#521000
b00000000000000000000000000110001 #
b00000000000000000000000000110001 $
b000000000000000000110001 &
#525000
1I
